{"id": "entity:pitivi-events-s-l", "file": "entity-pitivi-events-s-l.json", "kind": "entity", "name": "PITIVI EVENTS, S.L.", "cif": "B72703234", "city": "Reus", "province": "Tarragona", "organization": "Ajuntament de Valls", "record_count": 7, "visible_record_count": 7, "total_amount": 74015.70000000001, "display_amount": 24671.9, "display_count": 3, "display_source": "invoices", "years": {"2025": {"amount": 74015.70000000001, "count": 7}}, "sources": {"contracts": {"amount": 24671.9, "count": 3}, "supplier_spend": {"amount": 24671.9, "count": 1}, "invoices": {"amount": 24671.9, "count": 3}}, "records": [{"source": "supplier_spend", "source_label": "Despesa per proveïdor", "year": 2025, "amount": 24671.9, "date": "2025-12-31", "organization": "Ajuntament de Valls", "department": "", "counterparty": "PITIVI EVENTS, S.L.", "title": "Import total facturat pel proveïdor a 2025", "reference": "B72703234", "status": "", "is_cancelled": false, "source_file": "proveidors__despesa-per-prove-dor-2025.csv", "raw_fields": {"_id": "584", "NOM_ENS": "Ajuntament de Valls", "CODI_ENS": "4316130008", "PROVEIDOR": "PITIVI EVENTS, S.L.", "CIF": "B72703234", "POBL_ENT": "Reus", "PROV_ENT": "Tarragona", "IMPORT_FACTURAT": "24671.9000", "LATITUD": "41.2842776", "LONGITUD": "1.2476852"}}, {"source": "invoices", "source_label": "Factures", "year": 2025, "amount": 18137.9, "date": "2025-06-25T00:00:00", "organization": "Ajuntament de Valls", "department": "ACTIVITATS CULTURA", "counterparty": "PITIVI EVENTS, S.L.", "title": "PITIVI EVENTS, S.L., IMPORT FRA.53, ACTUACIÓ DEL GRUP DOCTOR PRATS A LA FESTA MAJOR DE SANT JOAN A L'APARCAMENT DE L'HORT DEL CARME LA NIT DEL 23 AL 24 DE JUNY", "reference": "53", "status": "Pagada", "is_cancelled": false, "source_file": "registre-factures__registre-de-factures-2025.csv", "raw_fields": {"_id": "3119", "NOM_ENS": "Ajuntament de Valls", "CODI_ENS": "4316130008", "REFERENCIA": "20250003125", "EXERCICI": "2025", "REFERENCIA_FACTURA": "53", "ESTAT_FACTURA": "Pagada", "DATA_PRESENTACIO": "2025-06-25T13:53:00", "DATA_REGISTRE": "2025-06-26T08:20:26", "DATA_FACTURA": "2025-06-25T00:00:00", "DESCRIPCIO": "PITIVI EVENTS, S.L., IMPORT FRA.53, ACTUACIÓ DEL GRUP DOCTOR PRATS A LA FESTA MAJOR DE SANT JOAN A L'APARCAMENT DE L'HORT DEL CARME LA NIT DEL 23 AL 24 DE JUNY", "TIPUS_ENTRADA": "Càrrec", "PROVEIDOR": "PITIVI EVENTS, S.L.", "DEPARTAMENT": "80400-ACTIVITATS CULTURA", "IMPORT_TOTAL": "18137.9000", "IMPORT_BRUT": "14990.0000", "IVA": "3147.9000", "DESCOMPTE": "0", "DATA_VENCIMENT": "2025-07-25T00:00:00", "DATA_INCORPORACIO": "2025-06-27T00:00:00", "DATA_COMPTABILITZACIO": "2025-07-04T00:00:00", "DATA_PAGAMENT": "2025-07-10T00:00:00", "LATITUD": "41.2842776", "LONGITUD": "1.2476852"}}, {"source": "invoices", "source_label": "Factures", "year": 2025, "amount": 4114.0, "date": "2025-06-25T00:00:00", "organization": "Ajuntament de Valls", "department": "ACTIVITATS CULTURA", "counterparty": "PITIVI EVENTS, S.L.", "title": "PITIVI EVENTS, S.L., IMPORT FRA.50, ACTUACIÓ DEL GRUP FENYA RAI, EL DIA 21 DE JUNY DE 2025 A LA PLAÇA DEL PATI", "reference": "50", "status": "Pagada", "is_cancelled": false, "source_file": "registre-factures__registre-de-factures-2025.csv", "raw_fields": {"_id": "3096", "NOM_ENS": "Ajuntament de Valls", "CODI_ENS": "4316130008", "REFERENCIA": "20250003124", "EXERCICI": "2025", "REFERENCIA_FACTURA": "50", "ESTAT_FACTURA": "Pagada", "DATA_PRESENTACIO": "2025-06-25T13:51:00", "DATA_REGISTRE": "2025-06-26T08:20:26", "DATA_FACTURA": "2025-06-25T00:00:00", "DESCRIPCIO": "PITIVI EVENTS, S.L., IMPORT FRA.50, ACTUACIÓ DEL GRUP FENYA RAI, EL DIA 21 DE JUNY DE 2025 A LA PLAÇA DEL PATI", "TIPUS_ENTRADA": "Càrrec", "PROVEIDOR": "PITIVI EVENTS, S.L.", "DEPARTAMENT": "80400-ACTIVITATS CULTURA", "IMPORT_TOTAL": "4114.0000", "IMPORT_BRUT": "3400.0000", "IVA": "714.0000", "DESCOMPTE": "0", "DATA_VENCIMENT": "2025-07-25T00:00:00", "DATA_INCORPORACIO": "2025-06-27T00:00:00", "DATA_COMPTABILITZACIO": "2025-07-04T00:00:00", "DATA_PAGAMENT": "2025-07-10T00:00:00", "LATITUD": "41.2842776", "LONGITUD": "1.2476852"}}, {"source": "invoices", "source_label": "Factures", "year": 2025, "amount": 2420.0, "date": "2025-06-25T00:00:00", "organization": "Ajuntament de Valls", "department": "ACTIVITATS CULTURA", "counterparty": "PITIVI EVENTS, S.L.", "title": "PITIVI EVENTS, S.L., IMPORT FRA.54, ACTUACIÓ DEL GRUP LA COSINA, EL DIA 21 DE JUNY A LA PLAÇA DEL PATI", "reference": "54", "status": "Pagada", "is_cancelled": false, "source_file": "registre-factures__registre-de-factures-2025.csv", "raw_fields": {"_id": "3126", "NOM_ENS": "Ajuntament de Valls", "CODI_ENS": "4316130008", "REFERENCIA": "20250003126", "EXERCICI": "2025", "REFERENCIA_FACTURA": "54", "ESTAT_FACTURA": "Pagada", "DATA_PRESENTACIO": "2025-06-25T13:55:00", "DATA_REGISTRE": "2025-06-26T08:20:26", "DATA_FACTURA": "2025-06-25T00:00:00", "DESCRIPCIO": "PITIVI EVENTS, S.L., IMPORT FRA.54, ACTUACIÓ DEL GRUP LA COSINA, EL DIA 21 DE JUNY A LA PLAÇA DEL PATI", "TIPUS_ENTRADA": "Càrrec", "PROVEIDOR": "PITIVI EVENTS, S.L.", "DEPARTAMENT": "80400-ACTIVITATS CULTURA", "IMPORT_TOTAL": "2420.0000", "IMPORT_BRUT": "2000.0000", "IVA": "420.0000", "DESCOMPTE": "0", "DATA_VENCIMENT": "2025-07-25T00:00:00", "DATA_INCORPORACIO": "2025-06-27T00:00:00", "DATA_COMPTABILITZACIO": "2025-07-04T00:00:00", "DATA_PAGAMENT": "2025-07-10T00:00:00", "LATITUD": "41.2842776", "LONGITUD": "1.2476852"}}, {"source": "contracts", "source_label": "Contractes menors", "year": 2025, "amount": 18137.9, "date": "2025-06-20T00:00:00", "organization": "Ajuntament de Valls", "department": "ACTIVITATS CULTURA", "counterparty": "PITIVI EVENTS, S.L.", "title": "Actuació del grup DOCTOR PRATS a la Festa Major de Sant Joan a l'aparcament de l'hort del Carme la nit del 23 al 24 de juny", "reference": "CM-2025-0001281", "status": "Serveis", "is_cancelled": false, "source_file": "contractacio__contractes-menors-2025.csv", "raw_fields": {"_id": "1208", "NOM_ENS": "Ajuntament de Valls", "CODI_ENS": "4316130008", "EXPEDIENT": "CM-2025-0001281", "DATA_ADJUDICACIO": "2025-06-20T00:00:00", "DESCRIPCIO": "Actuació del grup DOCTOR PRATS a la Festa Major de Sant Joan a l'aparcament de l'hort del Carme la nit del 23 al 24 de juny", "DEPARTAMENT": "ACTIVITATS CULTURA", "TIPUS": "Serveis", "NOM_ADJ": "PITIVI EVENTS, S.L.", "CIF_ADJ": "B72703234", "POBLACIO_ADJ": "Reus", "PROVINCIA_ADJ": "Tarragona", "IMPORT": "18137.9", "LATITUD": "41.2842776", "LONGITUD": "1.2476852"}}, {"source": "contracts", "source_label": "Contractes menors", "year": 2025, "amount": 4114.0, "date": "2025-06-13T00:00:00", "organization": "Ajuntament de Valls", "department": "ACTIVITATS CULTURA", "counterparty": "PITIVI EVENTS, S.L.", "title": "Actuació del grup FENYA RAI, el dia 21 de Juny de 2025 a la Plaça del Pati", "reference": "CM-2025-0001099", "status": "Artistic", "is_cancelled": false, "source_file": "contractacio__contractes-menors-2025.csv", "raw_fields": {"_id": "970", "NOM_ENS": "Ajuntament de Valls", "CODI_ENS": "4316130008", "EXPEDIENT": "CM-2025-0001099", "DATA_ADJUDICACIO": "2025-06-13T00:00:00", "DESCRIPCIO": "Actuació del grup FENYA RAI, el dia 21 de Juny de 2025 a la Plaça del Pati", "DEPARTAMENT": "ACTIVITATS CULTURA", "TIPUS": "Artistic", "NOM_ADJ": "PITIVI EVENTS, S.L.", "CIF_ADJ": "B72703234", "POBLACIO_ADJ": "Reus", "PROVINCIA_ADJ": "Tarragona", "IMPORT": "4114.0", "LATITUD": "41.2842776", "LONGITUD": "1.2476852"}}, {"source": "contracts", "source_label": "Contractes menors", "year": 2025, "amount": 2420.0, "date": "2025-06-13T00:00:00", "organization": "Ajuntament de Valls", "department": "ACTIVITATS CULTURA", "counterparty": "PITIVI EVENTS, S.L.", "title": "Actuació del grup LA COSINA, el dia 21 de Juny a la Plaça del Pati", "reference": "CM-2025-0001100", "status": "Artistic", "is_cancelled": false, "source_file": "contractacio__contractes-menors-2025.csv", "raw_fields": {"_id": "964", "NOM_ENS": "Ajuntament de Valls", "CODI_ENS": "4316130008", "EXPEDIENT": "CM-2025-0001100", "DATA_ADJUDICACIO": "2025-06-13T00:00:00", "DESCRIPCIO": "Actuació del grup LA COSINA, el dia 21 de Juny a la Plaça del Pati", "DEPARTAMENT": "ACTIVITATS CULTURA", "TIPUS": "Artistic", "NOM_ADJ": "PITIVI EVENTS, S.L.", "CIF_ADJ": "B72703234", "POBLACIO_ADJ": "Reus", "PROVINCIA_ADJ": "Tarragona", "IMPORT": "2420.0", "LATITUD": "41.2842776", "LONGITUD": "1.2476852"}}]}