{"id": "entity:iguzzini-illuminazione-iberica-s-a-u", "file": "entity-iguzzini-illuminazione-iberica-s-a-u.json", "kind": "entity", "name": "IGUZZINI ILLUMINAZIONE IBERICA, S.A.U.", "cif": "A58675208", "city": "Sant Cugat del Vallès", "province": "Barcelona", "organization": "Ajuntament de Valls", "record_count": 4, "visible_record_count": 4, "total_amount": 30028.100000000006, "display_amount": 10009.369999999999, "display_count": 2, "display_source": "invoices", "years": {"2023": {"amount": 30028.100000000006, "count": 4}}, "sources": {"contracts": {"amount": 10009.36, "count": 1}, "supplier_spend": {"amount": 10009.37, "count": 1}, "invoices": {"amount": 10009.369999999999, "count": 2}}, "records": [{"source": "supplier_spend", "source_label": "Despesa per proveïdor", "year": 2023, "amount": 10009.37, "date": "2023-12-31", "organization": "Ajuntament de Valls", "department": "", "counterparty": "IGUZZINI ILLUMINAZIONE IBERICA, S.A.U.", "title": "Import total facturat pel proveïdor a 2023", "reference": "A58675208", "status": "", "is_cancelled": false, "source_file": "proveidors__despesa-per-prove-dor-2023.csv", "raw_fields": {"_id": "106", "NOM_ENS": "Ajuntament de Valls", "CODI_ENS": "4316130008", "PROVEIDOR": "IGUZZINI ILLUMINAZIONE IBERICA, S.A.U.", "CIF": "A58675208", "POBL_ENT": "Sant Cugat del Vallès", "PROV_ENT": "Barcelona", "IMPORT_FACTURAT": "10009.3700", "LATITUD": "41.2842776", "LONGITUD": "1.2476852"}}, {"source": "invoices", "source_label": "Factures", "year": 2023, "amount": 6658.15, "date": "2023-11-30T00:00:00", "organization": "Ajuntament de Valls", "department": "40310-GRANS PROJECTES INTEGRALS", "counterparty": "IGUZZINI ILLUMINAZIONE IBERICA, S.A.U.", "title": "IGUZZINI ILLUMINAZIONE IBERICA, S.A.U., IMPORT FRA.23002401, SUBMINISTRAMENT SISTEMA IL·LUMINACIÓ OER ESPAIS EXPOSITIUS PLANTA 2A MUSEU DE VALLS", "reference": "23002401", "status": "Pagada", "is_cancelled": false, "source_file": "registre-factures__registre-de-factures-2023.csv", "raw_fields": {"_id": "4749", "NOM_ENS": "Ajuntament de Valls", "CODI_ENS": "4316130008", "REFERENCIA": "20230004763", "EXERCICI": "2023", "REFERENCIA_FACTURA": "23002401", "ESTAT_FACTURA": "Pagada", "DATA_PRESENTACIO": "2023-12-05T16:11:00", "DATA_REGISTRE": "2023-12-07T08:17:50", "DATA_FACTURA": "2023-11-30T00:00:00", "DESCRIPCIO": "IGUZZINI ILLUMINAZIONE IBERICA, S.A.U., IMPORT FRA.23002401, SUBMINISTRAMENT SISTEMA IL·LUMINACIÓ OER ESPAIS EXPOSITIUS PLANTA 2A MUSEU DE VALLS", "TIPUS_ENTRADA": "Càrrec", "PROVEIDOR": "IGUZZINI ILLUMINAZIONE IBERICA, S.A.U.", "DEPARTAMENT": "40310-GRANS PROJECTES INTEGRALS", "IMPORT_TOTAL": "6658.1500", "IMPORT_BRUT": "5502.6000", "IVA": "1155.5500", "DESCOMPTE": "0", "DATA_VENCIMENT": "2024-01-04T00:00:00", "DATA_INCORPORACIO": "2023-12-18T00:00:00", "DATA_COMPTABILITZACIO": "2023-12-22T00:00:00", "DATA_PAGAMENT": "2023-12-28T00:00:00", "LATITUD": "41.2842776", "LONGITUD": "1.2476852"}}, {"source": "invoices", "source_label": "Factures", "year": 2023, "amount": 3351.22, "date": "2023-11-15T00:00:00", "organization": "Ajuntament de Valls", "department": "40310-GRANS PROJECTES INTEGRALS", "counterparty": "IGUZZINI ILLUMINAZIONE IBERICA, S.A.U.", "title": "IGUZZINI ILLUMINAZIONE IBERICA, S.A.U., IMPORT FRA.23002276, SUBMINISTRAMENT SISTEMA IL·LUMINACIÓ OER ESPAIS EXPOSITIUS PLANTA 2A MUSEU DE VALLS", "reference": "23002276", "status": "Pagada", "is_cancelled": false, "source_file": "registre-factures__registre-de-factures-2023.csv", "raw_fields": {"_id": "4493", "NOM_ENS": "Ajuntament de Valls", "CODI_ENS": "4316130008", "REFERENCIA": "20230004492", "EXERCICI": "2023", "REFERENCIA_FACTURA": "23002276", "ESTAT_FACTURA": "Pagada", "DATA_PRESENTACIO": "2023-11-16T10:42:00", "DATA_REGISTRE": "2023-11-17T09:11:10", "DATA_FACTURA": "2023-11-15T00:00:00", "DESCRIPCIO": "IGUZZINI ILLUMINAZIONE IBERICA, S.A.U., IMPORT FRA.23002276, SUBMINISTRAMENT SISTEMA IL·LUMINACIÓ OER ESPAIS EXPOSITIUS PLANTA 2A MUSEU DE VALLS", "TIPUS_ENTRADA": "Càrrec", "PROVEIDOR": "IGUZZINI ILLUMINAZIONE IBERICA, S.A.U.", "DEPARTAMENT": "40310-GRANS PROJECTES INTEGRALS", "IMPORT_TOTAL": "3351.2200", "IMPORT_BRUT": "2769.6000", "IVA": "581.6200", "DESCOMPTE": "0", "DATA_VENCIMENT": "2023-12-16T00:00:00", "DATA_INCORPORACIO": "2023-12-22T00:00:00", "DATA_COMPTABILITZACIO": "2023-12-29T00:00:00", "DATA_PAGAMENT": "2024-01-03T00:00:00", "LATITUD": "41.2842776", "LONGITUD": "1.2476852"}}, {"source": "contracts", "source_label": "Contractes menors", "year": 2023, "amount": 10009.36, "date": "2023-10-27T00:00:00", "organization": "Ajuntament de Valls", "department": "ACTUACIONS PÚBLIQUES (Principal)", "counterparty": "IGUZZINI ILLUMINAZIONE IBERICA, S.A.U.", "title": "Subministrament sistema il·luminació oer espais expositius planta 2a Museu de Valls", "reference": "CM-2023-0001267", "status": "Subministrament", "is_cancelled": false, "source_file": "contractacio__contractes-menors-2023.csv", "raw_fields": {"_id": "1167", "NOM_ENS": "Ajuntament de Valls", "CODI_ENS": "4316130008", "EXPEDIENT": "CM-2023-0001267", "DATA_ADJUDICACIO": "2023-10-27T00:00:00", "DESCRIPCIO": "Subministrament sistema il·luminació oer espais expositius planta 2a Museu de Valls", "DEPARTAMENT": "ACTUACIONS PÚBLIQUES (Principal)", "TIPUS": "Subministrament", "NOM_ADJ": "IGUZZINI ILLUMINAZIONE IBERICA, S.A.U.", "CIF_ADJ": "A58675208", "POBLACIO_ADJ": "Sant Cugat del Vallès", "PROVINCIA_ADJ": "Barcelona", "IMPORT": "10009.36", "LATITUD": "41.2842776", "LONGITUD": "1.2476852"}}]}