{"id": "entity:codol-educacio-s-c-p", "file": "entity-codol-educacio-s-c-p.json", "kind": "entity", "name": "CODOL EDUCACIO, S.C.P.", "cif": "J43872811", "city": "Reus", "province": "Tarragona", "organization": "Ajuntament de Valls", "record_count": 9, "visible_record_count": 9, "total_amount": 34485.0, "display_amount": 11495.0, "display_count": 4, "display_source": "invoices", "years": {"2024": {"amount": 34485.0, "count": 9}}, "sources": {"contracts": {"amount": 11495.0, "count": 4}, "supplier_spend": {"amount": 11495.0, "count": 1}, "invoices": {"amount": 11495.0, "count": 4}}, "records": [{"source": "supplier_spend", "source_label": "Despesa per proveïdor", "year": 2024, "amount": 11495.0, "date": "2024-12-31", "organization": "Ajuntament de Valls", "department": "", "counterparty": "CODOL EDUCACIO, S.C.P.", "title": "Import total facturat pel proveïdor a 2024", "reference": "J43872811", "status": "", "is_cancelled": false, "source_file": "proveidors__despesa-per-prove-dor-2024.csv", "raw_fields": {"_id": "699", "NOM_ENS": "Ajuntament de Valls", "CODI_ENS": "4316130008", "PROVEIDOR": "CODOL EDUCACIO, S.C.P.", "CIF": "J43872811", "POBL_ENT": "Reus", "PROV_ENT": "Tarragona", "IMPORT_FACTURAT": "11495.0000", "LATITUD": "41.2842776", "LONGITUD": "1.2476852"}}, {"source": "invoices", "source_label": "Factures", "year": 2024, "amount": 6050.0, "date": "2024-12-21T00:00:00", "organization": "Ajuntament de Valls", "department": "SOSTENIBILITAT", "counterparty": "CODOL EDUCACIO, S.C.P.", "title": "CÒDOL EDUCACIÓ, S.C.P., IMPORT FRA.464-2024, ESPECTACLE GRÀCIES MARE TERRA", "reference": "464-2024", "status": "Pagada", "is_cancelled": false, "source_file": "registre-factures__registre-de-factures-2024.csv", "raw_fields": {"_id": "5963", "NOM_ENS": "Ajuntament de Valls", "CODI_ENS": "4316130008", "REFERENCIA": "20240005964", "EXERCICI": "2024", "REFERENCIA_FACTURA": "464-2024", "ESTAT_FACTURA": "Pagada", "DATA_PRESENTACIO": "2024-12-23T19:57:00", "DATA_REGISTRE": "2024-12-27T08:11:38", "DATA_FACTURA": "2024-12-21T00:00:00", "DESCRIPCIO": "CÒDOL EDUCACIÓ, S.C.P., IMPORT FRA.464-2024, ESPECTACLE GRÀCIES MARE TERRA", "TIPUS_ENTRADA": "Càrrec", "PROVEIDOR": "CODOL EDUCACIO, S.C.P.", "DEPARTAMENT": "51500-SOSTENIBILITAT", "IMPORT_TOTAL": "6050.0000", "IMPORT_BRUT": "5000.0000", "IVA": "1050.0000", "DESCOMPTE": "0", "DATA_VENCIMENT": "2025-01-22T00:00:00", "DATA_INCORPORACIO": "2024-12-31T00:00:00", "DATA_COMPTABILITZACIO": "2024-12-31T00:00:00", "DATA_PAGAMENT": "2025-01-23T00:00:00", "LATITUD": "41.2842776", "LONGITUD": "1.2476852"}}, {"source": "invoices", "source_label": "Factures", "year": 2024, "amount": 3712.5, "date": "2024-12-21T00:00:00", "organization": "Ajuntament de Valls", "department": "EDUCACIO", "counterparty": "CODOL EDUCACIO, S.C.P.", "title": "CODOL EDUCACIO, S.C.P., IMPORT FRA.465-2024, TALLERS CÚPULA DE LA SOSTENIBILITAT", "reference": "465-2024", "status": "Pagada", "is_cancelled": false, "source_file": "registre-factures__registre-de-factures-2024.csv", "raw_fields": {"_id": "5983", "NOM_ENS": "Ajuntament de Valls", "CODI_ENS": "4316130008", "REFERENCIA": "20240005965", "EXERCICI": "2024", "REFERENCIA_FACTURA": "465-2024", "ESTAT_FACTURA": "Pagada", "DATA_PRESENTACIO": "2024-12-23T20:03:00", "DATA_REGISTRE": "2024-12-27T08:11:38", "DATA_FACTURA": "2024-12-21T00:00:00", "DESCRIPCIO": "CODOL EDUCACIO, S.C.P., IMPORT FRA.465-2024, TALLERS CÚPULA DE LA SOSTENIBILITAT", "TIPUS_ENTRADA": "Càrrec", "PROVEIDOR": "CODOL EDUCACIO, S.C.P.", "DEPARTAMENT": "20100-EDUCACIO", "IMPORT_TOTAL": "3712.5000", "IMPORT_BRUT": "3375.0000", "IVA": "337.5000", "DESCOMPTE": "0", "DATA_VENCIMENT": "2025-01-22T00:00:00", "DATA_INCORPORACIO": "2024-12-30T00:00:00", "DATA_COMPTABILITZACIO": "2024-12-30T00:00:00", "DATA_PAGAMENT": "2025-01-13T00:00:00", "LATITUD": "41.2842776", "LONGITUD": "1.2476852"}}, {"source": "invoices", "source_label": "Factures", "year": 2024, "amount": 1210.0, "date": "2024-12-21T00:00:00", "organization": "Ajuntament de Valls", "department": "EDUCACIO", "counterparty": "CODOL EDUCACIO, S.C.P.", "title": "CODOL EDUCACIO, S.C.P., IMPORT FRA.466-2024, ACTIVITAT EN FAMÍLIA. CÚPULA DE LA SOSTENIBILITAT", "reference": "466-2024", "status": "Pagada", "is_cancelled": false, "source_file": "registre-factures__registre-de-factures-2024.csv", "raw_fields": {"_id": "5985", "NOM_ENS": "Ajuntament de Valls", "CODI_ENS": "4316130008", "REFERENCIA": "20240005975", "EXERCICI": "2024", "REFERENCIA_FACTURA": "466-2024", "ESTAT_FACTURA": "Pagada", "DATA_PRESENTACIO": "2024-12-23T20:17:00", "DATA_REGISTRE": "2024-12-27T08:12:19", "DATA_FACTURA": "2024-12-21T00:00:00", "DESCRIPCIO": "CODOL EDUCACIO, S.C.P., IMPORT FRA.466-2024, ACTIVITAT EN FAMÍLIA. CÚPULA DE LA SOSTENIBILITAT", "TIPUS_ENTRADA": "Càrrec", "PROVEIDOR": "CODOL EDUCACIO, S.C.P.", "DEPARTAMENT": "20100-EDUCACIO", "IMPORT_TOTAL": "1210.0000", "IMPORT_BRUT": "1000.0000", "IVA": "210.0000", "DESCOMPTE": "0", "DATA_VENCIMENT": "2025-01-22T00:00:00", "DATA_INCORPORACIO": "2024-12-31T00:00:00", "DATA_COMPTABILITZACIO": "2024-12-31T00:00:00", "DATA_PAGAMENT": "2025-01-23T00:00:00", "LATITUD": "41.2842776", "LONGITUD": "1.2476852"}}, {"source": "invoices", "source_label": "Factures", "year": 2024, "amount": 522.5, "date": "2024-12-21T00:00:00", "organization": "Ajuntament de Valls", "department": "EDUCACIO", "counterparty": "CODOL EDUCACIO, S.C.P.", "title": "CODOL EDUCACIO, S.C.P., IMPORT FRA.467-2024, TALLERS EXTRES CÚPULA DE LA SOSTENIBILITAT", "reference": "467-2024", "status": "Pagada", "is_cancelled": false, "source_file": "registre-factures__registre-de-factures-2024.csv", "raw_fields": {"_id": "5986", "NOM_ENS": "Ajuntament de Valls", "CODI_ENS": "4316130008", "REFERENCIA": "20240005974", "EXERCICI": "2024", "REFERENCIA_FACTURA": "467-2024", "ESTAT_FACTURA": "Pagada", "DATA_PRESENTACIO": "2024-12-23T20:11:00", "DATA_REGISTRE": "2024-12-27T08:12:19", "DATA_FACTURA": "2024-12-21T00:00:00", "DESCRIPCIO": "CODOL EDUCACIO, S.C.P., IMPORT FRA.467-2024, TALLERS EXTRES CÚPULA DE LA SOSTENIBILITAT", "TIPUS_ENTRADA": "Càrrec", "PROVEIDOR": "CODOL EDUCACIO, S.C.P.", "DEPARTAMENT": "20100-EDUCACIO", "IMPORT_TOTAL": "522.5000", "IMPORT_BRUT": "475.0000", "IVA": "47.5000", "DESCOMPTE": "0", "DATA_VENCIMENT": "2025-01-22T00:00:00", "DATA_INCORPORACIO": "2024-12-31T00:00:00", "DATA_COMPTABILITZACIO": "2024-12-31T00:00:00", "DATA_PAGAMENT": "2025-01-23T00:00:00", "LATITUD": "41.2842776", "LONGITUD": "1.2476852"}}, {"source": "contracts", "source_label": "Contractes menors", "year": 2024, "amount": 522.5, "date": "2024-12-20T00:00:00", "organization": "Ajuntament de Valls", "department": "EDUCACIÓ I POLÍTICA LINGÜÍSTICA", "counterparty": "CODOL EDUCACIO, S.C.P.", "title": "Tallers extres Cúpula de la SOStenibilitat .", "reference": "CM-2024-0001956", "status": "Serveis", "is_cancelled": false, "source_file": "contractacio__contractes-menors-2024.csv", "raw_fields": {"_id": "1749", "NOM_ENS": "Ajuntament de Valls", "CODI_ENS": "4316130008", "EXPEDIENT": "CM-2024-0001956", "DATA_ADJUDICACIO": "2024-12-20T00:00:00", "DESCRIPCIO": "Tallers extres Cúpula de la SOStenibilitat .", "DEPARTAMENT": "EDUCACIÓ I POLÍTICA LINGÜÍSTICA", "TIPUS": "Serveis", "NOM_ADJ": "CODOL EDUCACIO, S.C.P.", "CIF_ADJ": "J43872811", "POBLACIO_ADJ": "Reus", "PROVINCIA_ADJ": "Tarragona", "IMPORT": "522.5", "LATITUD": "41.2842776", "LONGITUD": "1.2476852"}}, {"source": "contracts", "source_label": "Contractes menors", "year": 2024, "amount": 3712.5, "date": "2024-11-08T00:00:00", "organization": "Ajuntament de Valls", "department": "EDUCACIÓ I POLÍTICA LINGÜÍSTICA", "counterparty": "CODOL EDUCACIO, S.C.P.", "title": "Tallers Cúpula de la SOStenibilitat", "reference": "CM-2024-0001678", "status": "Serveis", "is_cancelled": false, "source_file": "contractacio__contractes-menors-2024.csv", "raw_fields": {"_id": "1514", "NOM_ENS": "Ajuntament de Valls", "CODI_ENS": "4316130008", "EXPEDIENT": "CM-2024-0001678", "DATA_ADJUDICACIO": "2024-11-08T00:00:00", "DESCRIPCIO": "Tallers Cúpula de la SOStenibilitat", "DEPARTAMENT": "EDUCACIÓ I POLÍTICA LINGÜÍSTICA", "TIPUS": "Serveis", "NOM_ADJ": "CODOL EDUCACIO, S.C.P.", "CIF_ADJ": "J43872811", "POBLACIO_ADJ": "Reus", "PROVINCIA_ADJ": "Tarragona", "IMPORT": "3712.5", "LATITUD": "41.2842776", "LONGITUD": "1.2476852"}}, {"source": "contracts", "source_label": "Contractes menors", "year": 2024, "amount": 1210.0, "date": "2024-11-08T00:00:00", "organization": "Ajuntament de Valls", "department": "EDUCACIÓ I POLÍTICA LINGÜÍSTICA", "counterparty": "CODOL EDUCACIO, S.C.P.", "title": "Activitat en família. Cúpula de la SOStenibilitat", "reference": "CM-2024-0001680", "status": "Serveis", "is_cancelled": false, "source_file": "contractacio__contractes-menors-2024.csv", "raw_fields": {"_id": "1507", "NOM_ENS": "Ajuntament de Valls", "CODI_ENS": "4316130008", "EXPEDIENT": "CM-2024-0001680", "DATA_ADJUDICACIO": "2024-11-08T00:00:00", "DESCRIPCIO": "Activitat en família. Cúpula de la SOStenibilitat", "DEPARTAMENT": "EDUCACIÓ I POLÍTICA LINGÜÍSTICA", "TIPUS": "Serveis", "NOM_ADJ": "CODOL EDUCACIO, S.C.P.", "CIF_ADJ": "J43872811", "POBLACIO_ADJ": "Reus", "PROVINCIA_ADJ": "Tarragona", "IMPORT": "1210.0", "LATITUD": "41.2842776", "LONGITUD": "1.2476852"}}, {"source": "contracts", "source_label": "Contractes menors", "year": 2024, "amount": 6050.0, "date": "2024-10-31T00:00:00", "organization": "Ajuntament de Valls", "department": "MEDI AMBIENT", "counterparty": "CODOL EDUCACIO, S.C.P.", "title": "Espectacle GRÀCIES MARE TERRA", "reference": "CM-2024-0001628", "status": "Altres", "is_cancelled": false, "source_file": "contractacio__contractes-menors-2024.csv", "raw_fields": {"_id": "1458", "NOM_ENS": "Ajuntament de Valls", "CODI_ENS": "4316130008", "EXPEDIENT": "CM-2024-0001628", "DATA_ADJUDICACIO": "2024-10-31T00:00:00", "DESCRIPCIO": "Espectacle GRÀCIES MARE TERRA", "DEPARTAMENT": "MEDI AMBIENT", "TIPUS": "Altres", "NOM_ADJ": "CODOL EDUCACIO, S.C.P.", "CIF_ADJ": "J43872811", "POBLACIO_ADJ": "Reus", "PROVINCIA_ADJ": "Tarragona", "IMPORT": "6050.0", "LATITUD": "41.2842776", "LONGITUD": "1.2476852"}}]}