{"id": "entity:perez-angles-albert", "file": "entity-perez-angles-albert.json", "kind": "entity", "name": "PEREZ ANGLES, ALBERT", "cif": "****2476*", "city": "Valls", "province": "Tarragona", "organization": "Ajuntament de Valls", "record_count": 1, "visible_record_count": 1, "total_amount": 800.0, "display_amount": 800.0, "display_count": 1, "display_source": "supplier_spend", "years": {"2022": {"amount": 800.0, "count": 1}}, "sources": {"supplier_spend": {"amount": 800.0, "count": 1}}, "records": [{"source": "supplier_spend", "source_label": "Despesa per proveïdor", "year": 2022, "amount": 800.0, "date": "2022-12-31", "organization": "Ajuntament de Valls", "department": "", "counterparty": "PEREZ ANGLES, ALBERT", "title": "Import total facturat pel proveïdor a 2022", "reference": "****2476*", "status": "", "is_cancelled": false, "source_file": "proveidors__despesa-per-prove-dor-2022.csv", "raw_fields": {"_id": "429", "NOM_ENS": "Ajuntament de Valls", "CODI_ENS": "4316130008", "PROVEIDOR": "PEREZ ANGLES, ALBERT", "CIF": "****2476*", "POBL_ENT": "Valls", "PROV_ENT": "Tarragona", "IMPORT_FACTURAT": "800.0000", "LATITUD": "41.2842776", "LONGITUD": "1.2476852"}}]}