{"id": "entity:danico-events-2020-s-l", "file": "entity-danico-events-2020-s-l.json", "kind": "entity", "name": "DANICO EVENTS 2020, S.L.", "cif": "B25756214", "city": "Cervera", "province": "Lleida", "organization": "Ajuntament de Valls", "record_count": 12, "visible_record_count": 12, "total_amount": 75504.0, "display_amount": 25047.0, "display_count": 4, "display_source": "invoices", "years": {"2025": {"amount": 24684.0, "count": 3}, "2024": {"amount": 18876.0, "count": 3}, "2023": {"amount": 16335.0, "count": 3}, "2022": {"amount": 15609.0, "count": 3}}, "sources": {"contracts": {"amount": 25410.0, "count": 4}, "supplier_spend": {"amount": 25047.0, "count": 4}, "invoices": {"amount": 25047.0, "count": 4}}, "records": [{"source": "supplier_spend", "source_label": "Despesa per proveïdor", "year": 2025, "amount": 8228.0, "date": "2025-12-31", "organization": "Ajuntament de Valls", "department": "", "counterparty": "DANICO EVENTS 2020, S.L.", "title": "Import total facturat pel proveïdor a 2025", "reference": "B25756214", "status": "", "is_cancelled": false, "source_file": "proveidors__despesa-per-prove-dor-2025.csv", "raw_fields": {"_id": "489", "NOM_ENS": "Ajuntament de Valls", "CODI_ENS": "4316130008", "PROVEIDOR": "DANICO EVENTS 2020, S.L.", "CIF": "B25756214", "POBL_ENT": "Cervera", "PROV_ENT": "Lleida", "IMPORT_FACTURAT": "8228.0000", "LATITUD": "41.2842776", "LONGITUD": "1.2476852"}}, {"source": "contracts", "source_label": "Contractes menors", "year": 2025, "amount": 8228.0, "date": "2025-05-16T00:00:00", "organization": "Ajuntament de Valls", "department": "COMERÇ", "counterparty": "DANICO EVENTS 2020, S.L.", "title": "Lloguer de casetes de fusta per al Músic Valls Va de Vins 2025.", "reference": "CM-2025-0000910", "status": "Serveis", "is_cancelled": false, "source_file": "contractacio__contractes-menors-2025.csv", "raw_fields": {"_id": "1244", "NOM_ENS": "Ajuntament de Valls", "CODI_ENS": "4316130008", "EXPEDIENT": "CM-2025-0000910", "DATA_ADJUDICACIO": "2025-05-16T00:00:00", "DESCRIPCIO": "Lloguer de casetes de fusta per al Músic Valls Va de Vins 2025.", "DEPARTAMENT": "COMERÇ", "TIPUS": "Serveis", "NOM_ADJ": "DANICO EVENTS 2020, S.L.", "CIF_ADJ": "B25756214", "POBLACIO_ADJ": "Cervera", "PROVINCIA_ADJ": "Lleida", "IMPORT": "8228.0", "LATITUD": "41.2842776", "LONGITUD": "1.2476852"}}, {"source": "invoices", "source_label": "Factures", "year": 2025, "amount": 8228.0, "date": "2025-05-16T00:00:00", "organization": "Ajuntament de Valls", "department": "COMERÇ", "counterparty": "DANICO EVENTS 2020, S.L.", "title": "DANICO EVENTS 2020, S.L., IMPORT FRA.A34, LLOGUER DE CASETES DE FUSTA PER AL MÚSIC VALLS VA DE VINS 2025", "reference": "A34", "status": "Pagada", "is_cancelled": false, "source_file": "registre-factures__registre-de-factures-2025.csv", "raw_fields": {"_id": "2455", "NOM_ENS": "Ajuntament de Valls", "CODI_ENS": "4316130008", "REFERENCIA": "20250002440", "EXERCICI": "2025", "REFERENCIA_FACTURA": "A34", "ESTAT_FACTURA": "Pagada", "DATA_PRESENTACIO": "2025-05-16T12:34:00", "DATA_REGISTRE": "2025-05-19T07:44:48", "DATA_FACTURA": "2025-05-16T00:00:00", "DESCRIPCIO": "DANICO EVENTS 2020, S.L., IMPORT FRA.A34, LLOGUER DE CASETES DE FUSTA PER AL MÚSIC VALLS VA DE VINS 2025", "TIPUS_ENTRADA": "Càrrec", "PROVEIDOR": "DANICO EVENTS 2020, S.L.", "DEPARTAMENT": "11100-COMERÇ", "IMPORT_TOTAL": "8228.0000", "IMPORT_BRUT": "6800.0000", "IVA": "1428.0000", "DESCOMPTE": "0", "DATA_VENCIMENT": "2025-06-15T00:00:00", "DATA_INCORPORACIO": "2025-06-27T00:00:00", "DATA_COMPTABILITZACIO": "2025-07-04T00:00:00", "DATA_PAGAMENT": "2025-07-10T00:00:00", "LATITUD": "41.2842776", "LONGITUD": "1.2476852"}}, {"source": "supplier_spend", "source_label": "Despesa per proveïdor", "year": 2024, "amount": 6292.0, "date": "2024-12-31", "organization": "Ajuntament de Valls", "department": "", "counterparty": "DANICO EVENTS 2020, S.L.", "title": "Import total facturat pel proveïdor a 2024", "reference": "B25756214", "status": "", "is_cancelled": false, "source_file": "proveidors__despesa-per-prove-dor-2024.csv", "raw_fields": {"_id": "268", "NOM_ENS": "Ajuntament de Valls", "CODI_ENS": "4316130008", "PROVEIDOR": "DANICO EVENTS 2020, S.L.", "CIF": "B25756214", "POBL_ENT": "Cervera", "PROV_ENT": "Lleida", "IMPORT_FACTURAT": "6292.0000", "LATITUD": "41.2842776", "LONGITUD": "1.2476852"}}, {"source": "invoices", "source_label": "Factures", "year": 2024, "amount": 6292.0, "date": "2024-05-17T00:00:00", "organization": "Ajuntament de Valls", "department": "COMERÇ", "counterparty": "DANICO EVENTS 2020, S.L.", "title": "DANICO EVENTS 2020, S.L., IMPORT FRA.A21, LLOGUER ESTANDS FIRA DE VINS 2024.", "reference": "A21", "status": "Pagada", "is_cancelled": false, "source_file": "registre-factures__registre-de-factures-2024.csv", "raw_fields": {"_id": "2337", "NOM_ENS": "Ajuntament de Valls", "CODI_ENS": "4316130008", "REFERENCIA": "20240002328", "EXERCICI": "2024", "REFERENCIA_FACTURA": "A21", "ESTAT_FACTURA": "Pagada", "DATA_PRESENTACIO": "2024-05-17T10:01:00", "DATA_REGISTRE": "2024-05-20T08:19:55", "DATA_FACTURA": "2024-05-17T00:00:00", "DESCRIPCIO": "DANICO EVENTS 2020, S.L., IMPORT FRA.A21, LLOGUER ESTANDS FIRA DE VINS 2024.", "TIPUS_ENTRADA": "Càrrec", "PROVEIDOR": "DANICO EVENTS 2020, S.L.", "DEPARTAMENT": "11100-COMERÇ", "IMPORT_TOTAL": "6292.0000", "IMPORT_BRUT": "5200.0000", "IVA": "1092.0000", "DESCOMPTE": "0", "DATA_VENCIMENT": "2024-06-16T00:00:00", "DATA_INCORPORACIO": "2024-05-24T00:00:00", "DATA_COMPTABILITZACIO": "2024-05-31T00:00:00", "DATA_PAGAMENT": "2024-06-10T00:00:00", "LATITUD": "41.2842776", "LONGITUD": "1.2476852"}}, {"source": "contracts", "source_label": "Contractes menors", "year": 2024, "amount": 6292.0, "date": "2024-05-10T00:00:00", "organization": "Ajuntament de Valls", "department": "COMERÇ", "counterparty": "DANICO EVENTS 2020, S.L.", "title": "Lloguer estands Fira de Vins 2024.", "reference": "CM-2024-0000747", "status": "Altres", "is_cancelled": false, "source_file": "contractacio__contractes-menors-2024.csv", "raw_fields": {"_id": "667", "NOM_ENS": "Ajuntament de Valls", "CODI_ENS": "4316130008", "EXPEDIENT": "CM-2024-0000747", "DATA_ADJUDICACIO": "2024-05-10T00:00:00", "DESCRIPCIO": "Lloguer estands Fira de Vins 2024.", "DEPARTAMENT": "COMERÇ", "TIPUS": "Altres", "NOM_ADJ": "DANICO EVENTS 2020, S.L.", "CIF_ADJ": "B25756214", "POBLACIO_ADJ": "Cervera", "PROVINCIA_ADJ": "Lleida", "IMPORT": "6292.0", "LATITUD": "41.2842776", "LONGITUD": "1.2476852"}}, {"source": "supplier_spend", "source_label": "Despesa per proveïdor", "year": 2023, "amount": 5445.0, "date": "2023-12-31", "organization": "Ajuntament de Valls", "department": "", "counterparty": "DANICO EVENTS 2020, S.L.", "title": "Import total facturat pel proveïdor a 2023", "reference": "B25756214", "status": "", "is_cancelled": false, "source_file": "proveidors__despesa-per-prove-dor-2023.csv", "raw_fields": {"_id": "171", "NOM_ENS": "Ajuntament de Valls", "CODI_ENS": "4316130008", "PROVEIDOR": "DANICO EVENTS 2020, S.L.", "CIF": "B25756214", "POBL_ENT": "Cervera", "PROV_ENT": "Lleida", "IMPORT_FACTURAT": "5445.0000", "LATITUD": "41.2842776", "LONGITUD": "1.2476852"}}, {"source": "invoices", "source_label": "Factures", "year": 2023, "amount": 5445.0, "date": "2023-05-19T00:00:00", "organization": "Ajuntament de Valls", "department": "COMERÇ", "counterparty": "DANICO EVENTS 2020, S.L.", "title": "DANICO EVENTS 2020, SL, IMPORT FRA.A38, LLOGUER CASETES DE FUSTA PEL MÚSIC VALLS VA DE VINS 2023", "reference": "A38", "status": "Pagada", "is_cancelled": false, "source_file": "registre-factures__registre-de-factures-2023.csv", "raw_fields": {"_id": "2047", "NOM_ENS": "Ajuntament de Valls", "CODI_ENS": "4316130008", "REFERENCIA": "20230002041", "EXERCICI": "2023", "REFERENCIA_FACTURA": "A38", "ESTAT_FACTURA": "Pagada", "DATA_PRESENTACIO": "2023-05-19T10:06:00", "DATA_REGISTRE": "2023-05-22T08:18:15", "DATA_FACTURA": "2023-05-19T00:00:00", "DESCRIPCIO": "DANICO EVENTS 2020, SL, IMPORT FRA.A38, LLOGUER CASETES DE FUSTA PEL MÚSIC VALLS VA DE VINS 2023", "TIPUS_ENTRADA": "Càrrec", "PROVEIDOR": "DANICO EVENTS 2020, S.L.", "DEPARTAMENT": "11100-COMERÇ", "IMPORT_TOTAL": "5445.0000", "IMPORT_BRUT": "4500.0000", "IVA": "945.0000", "DESCOMPTE": "0", "DATA_VENCIMENT": "2023-06-18T00:00:00", "DATA_INCORPORACIO": "2023-05-26T00:00:00", "DATA_COMPTABILITZACIO": "2023-06-01T00:00:00", "DATA_PAGAMENT": "2023-06-07T00:00:00", "LATITUD": "41.2842776", "LONGITUD": "1.2476852"}}, {"source": "contracts", "source_label": "Contractes menors", "year": 2023, "amount": 5445.0, "date": "2023-04-06T00:00:00", "organization": "Ajuntament de Valls", "department": "COMERÇ", "counterparty": "DANICO EVENTS 2020, S.L.", "title": "Lloguer casetes de fusta pel Músic Valls va de vins 2023", "reference": "CM-2023-0000513", "status": "Altres", "is_cancelled": false, "source_file": "contractacio__contractes-menors-2023.csv", "raw_fields": {"_id": "443", "NOM_ENS": "Ajuntament de Valls", "CODI_ENS": "4316130008", "EXPEDIENT": "CM-2023-0000513", "DATA_ADJUDICACIO": "2023-04-06T00:00:00", "DESCRIPCIO": "Lloguer casetes de fusta pel Músic Valls va de vins 2023", "DEPARTAMENT": "COMERÇ", "TIPUS": "Altres", "NOM_ADJ": "DANICO EVENTS 2020, S.L.", "CIF_ADJ": "B25756214", "POBLACIO_ADJ": "Cervera", "PROVINCIA_ADJ": "Lleida", "IMPORT": "5445.0", "LATITUD": "41.2842776", "LONGITUD": "1.2476852"}}, {"source": "supplier_spend", "source_label": "Despesa per proveïdor", "year": 2022, "amount": 5082.0, "date": "2022-12-31", "organization": "Ajuntament de Valls", "department": "", "counterparty": "DANICO EVENTS 2020, S.L.", "title": "Import total facturat pel proveïdor a 2022", "reference": "B25756214", "status": "", "is_cancelled": false, "source_file": "proveidors__despesa-per-prove-dor-2022.csv", "raw_fields": {"_id": "173", "NOM_ENS": "Ajuntament de Valls", "CODI_ENS": "4316130008", "PROVEIDOR": "DANICO EVENTS 2020, S.L.", "CIF": "B25756214", "POBL_ENT": "Cervera", "PROV_ENT": "Lleida", "IMPORT_FACTURAT": "5082.0000", "LATITUD": "41.2842776", "LONGITUD": "1.2476852"}}, {"source": "invoices", "source_label": "Factures", "year": 2022, "amount": 5082.0, "date": "2022-05-24T00:00:00", "organization": "Ajuntament de Valls", "department": "COMERÇ", "counterparty": "DANICO EVENTS 2020, S.L.", "title": "DANICO EVENTS 2020, S.L., IMPORT FRA.A29, LLOGUER CASETES DE FUSTA PEL MÚSIC VALLS VA DE VINS 2022", "reference": "A29", "status": "Pagada", "is_cancelled": false, "source_file": "registre-factures__registre-de-factures-2022.csv", "raw_fields": {"_id": "1952", "NOM_ENS": "Ajuntament de Valls", "CODI_ENS": "4316130008", "REFERENCIA": "20220001949", "EXERCICI": "2022", "REFERENCIA_FACTURA": "A29", "ESTAT_FACTURA": "Pagada", "DATA_PRESENTACIO": "2022-05-25T08:15:04", "DATA_REGISTRE": "2022-05-25T08:15:04", "DATA_FACTURA": "2022-05-24T00:00:00", "DESCRIPCIO": "DANICO EVENTS 2020, S.L., IMPORT FRA.A29, LLOGUER CASETES DE FUSTA PEL MÚSIC VALLS VA DE VINS 2022", "TIPUS_ENTRADA": "Càrrec", "PROVEIDOR": "DANICO EVENTS 2020, S.L.", "DEPARTAMENT": "11100-COMERÇ", "IMPORT_TOTAL": "5082.0000", "IMPORT_BRUT": "4200.0000", "IVA": "882.0000", "DESCOMPTE": "0", "DATA_VENCIMENT": "2022-06-24T00:00:00", "DATA_INCORPORACIO": "2022-05-26T00:00:00", "DATA_COMPTABILITZACIO": "2022-06-02T00:00:00", "DATA_PAGAMENT": "2022-06-15T00:00:00", "LATITUD": "41.2842776", "LONGITUD": "1.2476852"}}, {"source": "contracts", "source_label": "Contractes menors", "year": 2022, "amount": 5445.0, "date": "2022-05-19T00:00:00", "organization": "Ajuntament de Valls", "department": "COMERÇ", "counterparty": "DANICO EVENTS 2020, S.L.", "title": "Lloguer casetes de fusta pel Músic Valls va de vins 2022", "reference": "CM-2022-0000640", "status": "Altres", "is_cancelled": false, "source_file": "contractacio__contractes-menors-2022.csv", "raw_fields": {"_id": "626", "NOM_ENS": "Ajuntament de Valls", "CODI_ENS": "4316130008", "EXPEDIENT": "CM-2022-0000640", "DATA_ADJUDICACIO": "2022-05-19T00:00:00", "DESCRIPCIO": "Lloguer casetes de fusta pel Músic Valls va de vins 2022", "DEPARTAMENT": "COMERÇ", "TIPUS": "Altres", "NOM_ADJ": "DANICO EVENTS 2020, S.L.", "CIF_ADJ": "B25756214", "POBLACIO_ADJ": "Cervera", "PROVINCIA_ADJ": "Lleida", "IMPORT": "5445.0", "LATITUD": "41.2842776", "LONGITUD": "1.2476852"}}]}