{"id": "entity:tek-3000-wrcp-s-l", "file": "entity-tek-3000-wrcp-s-l.json", "kind": "entity", "name": "TEK 3000 WRCP S.L", "cif": "B55687156", "city": "Valls", "province": "Tarragona", "organization": "Ajuntament de Valls", "record_count": 14, "visible_record_count": 14, "total_amount": 58427.56, "display_amount": 19475.63, "display_count": 6, "display_source": "invoices", "years": {"2021": {"amount": 15567.48, "count": 5}, "2020": {"amount": 42860.08, "count": 9}}, "sources": {"contracts": {"amount": 19476.3, "count": 6}, "supplier_spend": {"amount": 19475.629999999997, "count": 2}, "invoices": {"amount": 19475.63, "count": 6}}, "records": [{"source": "supplier_spend", "source_label": "Despesa per proveïdor", "year": 2021, "amount": 5189.16, "date": "2021-12-31", "organization": "Ajuntament de Valls", "department": "", "counterparty": "TEK 3000 WRCP S.L", "title": "Import total facturat pel proveïdor a 2021", "reference": "B55687156", "status": "", "is_cancelled": false, "source_file": "proveidors__despesa-per-prove-dor-2021.csv", "raw_fields": {"_id": "225", "NOM_ENS": "Ajuntament de Valls", "CODI_ENS": "4316130008", "PROVEIDOR": "TEK 3000 WRCP S.L", "CIF": "B55687156", "POBL_ENT": "Valls", "PROV_ENT": "Tarragona", "IMPORT_FACTURAT": "5189.1600", "LATITUD": "41.2842776", "LONGITUD": "1.2476852"}}, {"source": "contracts", "source_label": "Contractes menors", "year": 2021, "amount": 1689.16, "date": "2021-12-23T00:00:00", "organization": "Ajuntament de Valls", "department": "PROTECCIÓ CIVIL", "counterparty": "TEK 3000 WRCP S.L", "title": "Adquisició llums autònoms per a AVPCV", "reference": "CM-2021-0001451", "status": "Subministrament", "is_cancelled": false, "source_file": "contractacio__contractes-menors-2021.csv", "raw_fields": {"_id": "1358", "NOM_ENS": "Ajuntament de Valls", "CODI_ENS": "4316130008", "EXPEDIENT": "CM-2021-0001451", "DATA_ADJUDICACIO": "2021-12-23T00:00:00", "DESCRIPCIO": "Adquisició llums autònoms per a AVPCV", "DEPARTAMENT": "PROTECCIÓ CIVIL", "TIPUS": "Subministrament", "NOM_ADJ": "TEK 3000 WRCP S.L", "CIF_ADJ": "B55687156", "POBLACIO_ADJ": "Valls", "PROVINCIA_ADJ": "Tarragona", "IMPORT": "1689.16", "LATITUD": "41.2842776", "LONGITUD": "1.2476852"}}, {"source": "invoices", "source_label": "Factures", "year": 2021, "amount": 1689.16, "date": "2021-12-15T00:00:00", "organization": "Ajuntament de Valls", "department": "50106-PROTECCIO CIVIL", "counterparty": "TEK 3000 WRCP S.L", "title": "TEK 3000 WRCP S.L, IMPORT FRA.A00060, ADQUISICIÓ LLUMS AUTÒNOMS PER A AVPCV", "reference": "A00060", "status": "Pagada", "is_cancelled": false, "source_file": "registre-factures__registre-de-factures-2021.csv", "raw_fields": {"_id": "4765", "NOM_ENS": "Ajuntament de Valls", "CODI_ENS": "4316130008", "REFERENCIA": "20210004746", "EXERCICI": "2021", "REFERENCIA_FACTURA": "A00060", "ESTAT_FACTURA": "Pagada", "DATA_PRESENTACIO": "2021-12-16T07:45:10", "DATA_REGISTRE": "2021-12-16T07:45:10", "DATA_FACTURA": "2021-12-15T00:00:00", "DESCRIPCIO": "TEK 3000 WRCP S.L, IMPORT FRA.A00060, ADQUISICIÓ LLUMS AUTÒNOMS PER A AVPCV", "TIPUS_ENTRADA": "Càrrec", "PROVEIDOR": "TEK 3000 WRCP S.L", "DEPARTAMENT": "50106-PROTECCIO CIVIL", "IMPORT_TOTAL": "1689.1600", "IMPORT_BRUT": "1396.0000", "IVA": "293.1600", "DESCOMPTE": "0", "DATA_VENCIMENT": "2022-01-15T00:00:00", "DATA_INCORPORACIO": "2021-12-27T00:00:00", "DATA_COMPTABILITZACIO": "2021-12-30T00:00:00", "DATA_PAGAMENT": "2022-01-11T00:00:00", "LATITUD": "41.2842776", "LONGITUD": "1.2476852"}}, {"source": "invoices", "source_label": "Factures", "year": 2021, "amount": 3500.0, "date": "2021-03-19T00:00:00", "organization": "Ajuntament de Valls", "department": "50106-PROTECCIO CIVIL", "counterparty": "TEK 3000 WRCP S.L", "title": "TEK 3000 WRCP S.L, IMPORT FRA.A0018, MASCARETES FFP2 BLANQUES", "reference": "A0018", "status": "Pagada", "is_cancelled": false, "source_file": "registre-factures__registre-de-factures-2021.csv", "raw_fields": {"_id": "1009", "NOM_ENS": "Ajuntament de Valls", "CODI_ENS": "4316130008", "REFERENCIA": "20210001009", "EXERCICI": "2021", "REFERENCIA_FACTURA": "A0018", "ESTAT_FACTURA": "Pagada", "DATA_PRESENTACIO": "2021-03-22T07:56:38", "DATA_REGISTRE": "2021-03-22T07:56:38", "DATA_FACTURA": "2021-03-19T00:00:00", "DESCRIPCIO": "TEK 3000 WRCP S.L, IMPORT FRA.A0018, MASCARETES FFP2 BLANQUES", "TIPUS_ENTRADA": "Càrrec", "PROVEIDOR": "TEK 3000 WRCP S.L", "DEPARTAMENT": "50106-PROTECCIO CIVIL", "IMPORT_TOTAL": "3500.0000", "IMPORT_BRUT": "3500.0000", "IVA": "0", "DESCOMPTE": "0", "DATA_VENCIMENT": "2021-04-21T00:00:00", "DATA_INCORPORACIO": "2021-03-26T00:00:00", "DATA_COMPTABILITZACIO": "2021-04-01T00:00:00", "DATA_PAGAMENT": "2021-04-16T00:00:00", "LATITUD": "41.2842776", "LONGITUD": "1.2476852"}}, {"source": "contracts", "source_label": "Contractes menors", "year": 2021, "amount": 3500.0, "date": "2021-01-14T00:00:00", "organization": "Ajuntament de Valls", "department": "PROTECCIÓ CIVIL", "counterparty": "TEK 3000 WRCP S.L", "title": "Mascaretes FFP2 Blanques", "reference": "CM-2021-0000010", "status": "Subministrament", "is_cancelled": false, "source_file": "contractacio__contractes-menors-2021.csv", "raw_fields": {"_id": "43", "NOM_ENS": "Ajuntament de Valls", "CODI_ENS": "4316130008", "EXPEDIENT": "CM-2021-0000010", "DATA_ADJUDICACIO": "2021-01-14T00:00:00", "DESCRIPCIO": "Mascaretes FFP2 Blanques", "DEPARTAMENT": "PROTECCIÓ CIVIL", "TIPUS": "Subministrament", "NOM_ADJ": "TEK 3000 WRCP S.L", "CIF_ADJ": "B55687156", "POBLACIO_ADJ": "Valls", "PROVINCIA_ADJ": "Tarragona", "IMPORT": "3500.0", "LATITUD": "41.2842776", "LONGITUD": "1.2476852"}}, {"source": "supplier_spend", "source_label": "Despesa per proveïdor", "year": 2020, "amount": 14286.47, "date": "2020-12-31", "organization": "Ajuntament de Valls", "department": "", "counterparty": "TEK 3000 WRCP S.L", "title": "Import total facturat pel proveïdor a 2020", "reference": "B55687156", "status": "", "is_cancelled": false, "source_file": "proveidors__despesa-per-prove-dor-2020.csv", "raw_fields": {"_id": "60", "NOM_ENS": "Ajuntament de Valls", "CODI_ENS": "4316130008", "PROVEIDOR": "TEK 3000 WRCP S.L", "CIF": "B55687156", "POBL_ENT": "Valls", "PROV_ENT": "Tarragona", "IMPORT_FACTURAT": "14286.4700", "LATITUD": "41.2842776", "LONGITUD": "1.2476852"}}, {"source": "contracts", "source_label": "Contractes menors", "year": 2020, "amount": 7211.6, "date": "2020-09-03T00:00:00", "organization": "Ajuntament de Valls", "department": "PROTECCIÓ CIVIL", "counterparty": "TEK 3000 WRCP S.L", "title": "Compra mascaretes FFP\" TEK 3000 14-4-2020", "reference": "CM-2020-0000499", "status": "Subministrament", "is_cancelled": false, "source_file": "contractacio__contractes-menors-2020.csv", "raw_fields": {"_id": "796", "NOM_ENS": "Ajuntament de Valls", "CODI_ENS": "4316130008", "EXPEDIENT": "CM-2020-0000499", "DATA_ADJUDICACIO": "2020-09-03T00:00:00", "DESCRIPCIO": "Compra mascaretes FFP\" TEK 3000 14-4-2020", "DEPARTAMENT": "PROTECCIÓ CIVIL", "TIPUS": "Subministrament", "NOM_ADJ": "TEK 3000 WRCP S.L", "CIF_ADJ": "B55687156", "POBLACIO_ADJ": "Valls", "PROVINCIA_ADJ": "Tarragona", "IMPORT": "7211.6", "LATITUD": "41.2842776", "LONGITUD": "1.2476852"}}, {"source": "contracts", "source_label": "Contractes menors", "year": 2020, "amount": 2388.0, "date": "2020-08-27T00:00:00", "organization": "Ajuntament de Valls", "department": "PROTECCIÓ CIVIL", "counterparty": "TEK 3000 WRCP S.L", "title": "Adquisició mascaretes FFP2 TEC3000 agost 2020", "reference": "CM-2020-0000924", "status": "Subministrament", "is_cancelled": false, "source_file": "contractacio__contractes-menors-2020.csv", "raw_fields": {"_id": "781", "NOM_ENS": "Ajuntament de Valls", "CODI_ENS": "4316130008", "EXPEDIENT": "CM-2020-0000924", "DATA_ADJUDICACIO": "2020-08-27T00:00:00", "DESCRIPCIO": "Adquisició mascaretes FFP2 TEC3000 agost 2020", "DEPARTAMENT": "PROTECCIÓ CIVIL", "TIPUS": "Subministrament", "NOM_ADJ": "TEK 3000 WRCP S.L", "CIF_ADJ": "B55687156", "POBLACIO_ADJ": "Valls", "PROVINCIA_ADJ": "Tarragona", "IMPORT": "2388.0", "LATITUD": "41.2842776", "LONGITUD": "1.2476852"}}, {"source": "invoices", "source_label": "Factures", "year": 2020, "amount": 2387.33, "date": "2020-08-19T00:00:00", "organization": "Ajuntament de Valls", "department": "50106-PROTECCIO CIVIL", "counterparty": "TEK 3000 WRCP S.L", "title": "TEK 3000 WRCP S.L, IMPORT FRA.A00033, ADQUISICIÓ MASCARETES FFP2 TEC3000 AGOST 2020", "reference": "A00033", "status": "Pagada", "is_cancelled": false, "source_file": "registre-factures__registre-de-factures-2020.csv", "raw_fields": {"_id": "4497", "NOM_ENS": "Ajuntament de Valls", "CODI_ENS": "4316130008", "REFERENCIA": "20200004497", "EXERCICI": "2020", "REFERENCIA_FACTURA": "A00033", "ESTAT_FACTURA": "Pagada", "DATA_PRESENTACIO": "2020-12-09T00:00:00", "DATA_REGISTRE": "2020-12-09T00:00:00", "DATA_FACTURA": "2020-08-19T00:00:00", "DESCRIPCIO": "TEK 3000 WRCP S.L, IMPORT FRA.A00033, ADQUISICIÓ MASCARETES FFP2 TEC3000 AGOST 2020", "TIPUS_ENTRADA": "Càrrec", "PROVEIDOR": "TEK 3000 WRCP S.L", "DEPARTAMENT": "50106-PROTECCIO CIVIL", "IMPORT_TOTAL": "2387.3300", "IMPORT_BRUT": "1973.0000", "IVA": "414.3300", "DESCOMPTE": "0", "DATA_VENCIMENT": "2021-01-08T00:00:00", "DATA_INCORPORACIO": "2020-12-11T00:00:00", "DATA_COMPTABILITZACIO": "2020-12-17T00:00:00", "DATA_PAGAMENT": "2021-01-11T00:00:00", "LATITUD": "41.2842776", "LONGITUD": "1.2476852"}}, {"source": "invoices", "source_label": "Factures", "year": 2020, "amount": 7211.6, "date": "2020-05-18T00:00:00", "organization": "Ajuntament de Valls", "department": "50106-PROTECCIO CIVIL", "counterparty": "TEK 3000 WRCP S.L", "title": "TEK 3000 WRCP, SL, IMPORT FRA.A00020, COMPRA MASCARETES FFP' TEK 3000 14-4-2020", "reference": "A00020", "status": "Pagada", "is_cancelled": false, "source_file": "registre-factures__registre-de-factures-2020.csv", "raw_fields": {"_id": "1755", "NOM_ENS": "Ajuntament de Valls", "CODI_ENS": "4316130008", "REFERENCIA": "20200001755", "EXERCICI": "2020", "REFERENCIA_FACTURA": "A00020", "ESTAT_FACTURA": "Pagada", "DATA_PRESENTACIO": "2020-05-18T10:56:48", "DATA_REGISTRE": "2020-05-18T10:56:48", "DATA_FACTURA": "2020-05-18T00:00:00", "DESCRIPCIO": "TEK 3000 WRCP, SL, IMPORT FRA.A00020, COMPRA MASCARETES FFP' TEK 3000 14-4-2020", "TIPUS_ENTRADA": "Càrrec", "PROVEIDOR": "TEK 3000 WRCP S.L", "DEPARTAMENT": "50106-PROTECCIO CIVIL", "IMPORT_TOTAL": "7211.6000", "IMPORT_BRUT": "5960.0000", "IVA": "1251.6000", "DESCOMPTE": "0", "DATA_VENCIMENT": "2020-06-17T00:00:00", "DATA_INCORPORACIO": "2020-09-07T00:00:00", "DATA_COMPTABILITZACIO": "2020-09-10T00:00:00", "DATA_PAGAMENT": "2020-09-24T00:00:00", "LATITUD": "41.2842776", "LONGITUD": "1.2476852"}}, {"source": "contracts", "source_label": "Contractes menors", "year": 2020, "amount": 3605.8, "date": "2020-05-07T00:00:00", "organization": "Ajuntament de Valls", "department": "PROTECCIÓ CIVIL", "counterparty": "TEK 3000 WRCP S.L", "title": "Mascaretes FFP2 1.000 uts. TEK3000 24-4-20", "reference": "CM-2020-0000539", "status": "Subministrament", "is_cancelled": false, "source_file": "contractacio__contractes-menors-2020.csv", "raw_fields": {"_id": "472", "NOM_ENS": "Ajuntament de Valls", "CODI_ENS": "4316130008", "EXPEDIENT": "CM-2020-0000539", "DATA_ADJUDICACIO": "2020-05-07T00:00:00", "DESCRIPCIO": "Mascaretes FFP2 1.000 uts. TEK3000 24-4-20", "DEPARTAMENT": "PROTECCIÓ CIVIL", "TIPUS": "Subministrament", "NOM_ADJ": "TEK 3000 WRCP S.L", "CIF_ADJ": "B55687156", "POBLACIO_ADJ": "Valls", "PROVINCIA_ADJ": "Tarragona", "IMPORT": "3605.8", "LATITUD": "41.2842776", "LONGITUD": "1.2476852"}}, {"source": "invoices", "source_label": "Factures", "year": 2020, "amount": 3605.8, "date": "2020-04-29T00:00:00", "organization": "Ajuntament de Valls", "department": "50106-PROTECCIO CIVIL", "counterparty": "TEK 3000 WRCP S.L", "title": "TEK 3000 WRCP S.L, IMPORT FRA.A00016, MASCARETES FFP2 1.000 UTS. TEK3000 24-4-20", "reference": "A00016", "status": "Pagada", "is_cancelled": false, "source_file": "registre-factures__registre-de-factures-2020.csv", "raw_fields": {"_id": "1503", "NOM_ENS": "Ajuntament de Valls", "CODI_ENS": "4316130008", "REFERENCIA": "20200001504", "EXERCICI": "2020", "REFERENCIA_FACTURA": "A00016", "ESTAT_FACTURA": "Pagada", "DATA_PRESENTACIO": "2020-04-29T00:00:00", "DATA_REGISTRE": "2020-04-29T00:00:00", "DATA_FACTURA": "2020-04-29T00:00:00", "DESCRIPCIO": "TEK 3000 WRCP S.L, IMPORT FRA.A00016, MASCARETES FFP2 1.000 UTS. TEK3000 24-4-20", "TIPUS_ENTRADA": "Càrrec", "PROVEIDOR": "TEK 3000 WRCP S.L", "DEPARTAMENT": "50106-PROTECCIO CIVIL", "IMPORT_TOTAL": "3605.8000", "IMPORT_BRUT": "2980.0000", "IVA": "625.8000", "DESCOMPTE": "0", "DATA_VENCIMENT": "2020-05-29T00:00:00", "DATA_INCORPORACIO": "2020-05-10T00:00:00", "DATA_COMPTABILITZACIO": "2020-05-14T00:00:00", "DATA_PAGAMENT": "2020-06-03T00:00:00", "LATITUD": "41.2842776", "LONGITUD": "1.2476852"}}, {"source": "invoices", "source_label": "Factures", "year": 2020, "amount": 1081.74, "date": "2020-04-29T00:00:00", "organization": "Ajuntament de Valls", "department": "50106-PROTECCIO CIVIL", "counterparty": "TEK 3000 WRCP S.L", "title": "TEK 3000 WRCP S.L, IMPORT FRA.A00015, 300 MASCARETES FFP2 TREK3000", "reference": "A00015", "status": "Pagada", "is_cancelled": false, "source_file": "registre-factures__registre-de-factures-2020.csv", "raw_fields": {"_id": "1470", "NOM_ENS": "Ajuntament de Valls", "CODI_ENS": "4316130008", "REFERENCIA": "20200001470", "EXERCICI": "2020", "REFERENCIA_FACTURA": "A00015", "ESTAT_FACTURA": "Pagada", "DATA_PRESENTACIO": "2020-04-29T00:00:00", "DATA_REGISTRE": "2020-04-29T00:00:00", "DATA_FACTURA": "2020-04-29T00:00:00", "DESCRIPCIO": "TEK 3000 WRCP S.L, IMPORT FRA.A00015, 300 MASCARETES FFP2 TREK3000", "TIPUS_ENTRADA": "Càrrec", "PROVEIDOR": "TEK 3000 WRCP S.L", "DEPARTAMENT": "50106-PROTECCIO CIVIL", "IMPORT_TOTAL": "1081.7400", "IMPORT_BRUT": "894.0000", "IVA": "187.7400", "DESCOMPTE": "0", "DATA_VENCIMENT": "2020-05-29T00:00:00", "DATA_INCORPORACIO": "2020-05-10T00:00:00", "DATA_COMPTABILITZACIO": "2020-05-14T00:00:00", "DATA_PAGAMENT": "2020-06-03T00:00:00", "LATITUD": "41.2842776", "LONGITUD": "1.2476852"}}, {"source": "contracts", "source_label": "Contractes menors", "year": 2020, "amount": 1081.74, "date": "2020-04-21T00:00:00", "organization": "Ajuntament de Valls", "department": "PROTECCIÓ CIVIL", "counterparty": "TEK 3000 WRCP S.L", "title": "300 mascaretes FFP2 Trek3000", "reference": "CM-2020-0000496", "status": "Subministrament", "is_cancelled": false, "source_file": "contractacio__contractes-menors-2020.csv", "raw_fields": {"_id": "424", "NOM_ENS": "Ajuntament de Valls", "CODI_ENS": "4316130008", "EXPEDIENT": "CM-2020-0000496", "DATA_ADJUDICACIO": "2020-04-21T00:00:00", "DESCRIPCIO": "300 mascaretes FFP2 Trek3000", "DEPARTAMENT": "PROTECCIÓ CIVIL", "TIPUS": "Subministrament", "NOM_ADJ": "TEK 3000 WRCP S.L", "CIF_ADJ": "B55687156", "POBLACIO_ADJ": "Valls", "PROVINCIA_ADJ": "Tarragona", "IMPORT": "1081.74", "LATITUD": "41.2842776", "LONGITUD": "1.2476852"}}]}