{"id": "entity:vives-corbella-pilar", "file": "entity-vives-corbella-pilar.json", "kind": "entity", "name": "VIVES CORBELLA, PILAR", "cif": "****9989*", "city": "Valls", "province": "Tarragona", "organization": "Ajuntament de Valls", "record_count": 8, "visible_record_count": 8, "total_amount": 1752.0, "display_amount": 584.0, "display_count": 3, "display_source": "invoices", "years": {"2023": {"amount": 1125.0, "count": 3}, "2020": {"amount": 627.0, "count": 5}}, "sources": {"contracts": {"amount": 584.0, "count": 3}, "supplier_spend": {"amount": 584.0, "count": 2}, "invoices": {"amount": 584.0, "count": 3}}, "records": [{"source": "supplier_spend", "source_label": "Despesa per proveïdor", "year": 2023, "amount": 375.0, "date": "2023-12-31", "organization": "Ajuntament de Valls", "department": "", "counterparty": "VIVES CORBELLA, PILAR", "title": "Import total facturat pel proveïdor a 2023", "reference": "****9989*", "status": "", "is_cancelled": false, "source_file": "proveidors__despesa-per-prove-dor-2023.csv", "raw_fields": {"_id": "565", "NOM_ENS": "Ajuntament de Valls", "CODI_ENS": "4316130008", "PROVEIDOR": "VIVES CORBELLA, PILAR", "CIF": "****9989*", "POBL_ENT": "Valls", "PROV_ENT": "Tarragona", "IMPORT_FACTURAT": "375.0000", "LATITUD": "41.2842776", "LONGITUD": "1.2476852"}}, {"source": "invoices", "source_label": "Factures", "year": 2023, "amount": 375.0, "date": "2023-03-31T00:00:00", "organization": "Ajuntament de Valls", "department": "21200-ACCIO CIVICA", "counterparty": "VIVES CORBELLA, PILAR", "title": "PILAR VIVES CORBELLA, IMPORT FRA.1, CURS D'HISTÒRIA DE FEBRER A MAÇ 2023", "reference": "1", "status": "Pagada", "is_cancelled": false, "source_file": "registre-factures__registre-de-factures-2023.csv", "raw_fields": {"_id": "1298", "NOM_ENS": "Ajuntament de Valls", "CODI_ENS": "4316130008", "REFERENCIA": "20230001297", "EXERCICI": "2023", "REFERENCIA_FACTURA": "1", "ESTAT_FACTURA": "Pagada", "DATA_PRESENTACIO": "2023-03-31T00:00:00", "DATA_REGISTRE": "2023-03-31T00:00:00", "DATA_FACTURA": "2023-03-31T00:00:00", "DESCRIPCIO": "PILAR VIVES CORBELLA, IMPORT FRA.1, CURS D'HISTÒRIA DE FEBRER A MAÇ 2023", "TIPUS_ENTRADA": "Càrrec", "PROVEIDOR": "VIVES CORBELLA, PILAR", "DEPARTAMENT": "21200-ACCIO CIVICA", "IMPORT_TOTAL": "375.0000", "IMPORT_BRUT": "375.0000", "IVA": "0", "DESCOMPTE": "56.2500", "DATA_VENCIMENT": "2023-04-30T00:00:00", "DATA_INCORPORACIO": "2023-04-04T00:00:00", "DATA_COMPTABILITZACIO": "2023-04-13T00:00:00", "DATA_PAGAMENT": "2023-04-18T00:00:00", "LATITUD": "41.2842776", "LONGITUD": "1.2476852"}}, {"source": "contracts", "source_label": "Contractes menors", "year": 2023, "amount": 375.0, "date": "2023-03-09T00:00:00", "organization": "Ajuntament de Valls", "department": "ACCIÓ CÍVICA", "counterparty": "VIVES CORBELLA, PILAR", "title": "Curs d'història de febrer a maç 2023", "reference": "CM-2023-0000362", "status": "Serveis", "is_cancelled": false, "source_file": "contractacio__contractes-menors-2023.csv", "raw_fields": {"_id": "356", "NOM_ENS": "Ajuntament de Valls", "CODI_ENS": "4316130008", "EXPEDIENT": "CM-2023-0000362", "DATA_ADJUDICACIO": "2023-03-09T00:00:00", "DESCRIPCIO": "Curs d'història de febrer a maç 2023", "DEPARTAMENT": "ACCIÓ CÍVICA", "TIPUS": "Serveis", "NOM_ADJ": "VIVES CORBELLA, PILAR", "CIF_ADJ": "****9989*", "POBLACIO_ADJ": "Valls", "PROVINCIA_ADJ": "Tarragona", "IMPORT": "375.0", "LATITUD": "41.2842776", "LONGITUD": "1.2476852"}}, {"source": "supplier_spend", "source_label": "Despesa per proveïdor", "year": 2020, "amount": 209.0, "date": "2020-12-31", "organization": "Ajuntament de Valls", "department": "", "counterparty": "VIVES CORBELLA, PILAR", "title": "Import total facturat pel proveïdor a 2020", "reference": "****9989*", "status": "", "is_cancelled": false, "source_file": "proveidors__despesa-per-prove-dor-2020.csv", "raw_fields": {"_id": "456", "NOM_ENS": "Ajuntament de Valls", "CODI_ENS": "4316130008", "PROVEIDOR": "VIVES CORBELLA, PILAR", "CIF": "****9989*", "POBL_ENT": "Valls", "PROV_ENT": "Tarragona", "IMPORT_FACTURAT": "209.0000", "LATITUD": "41.2842776", "LONGITUD": "1.2476852"}}, {"source": "invoices", "source_label": "Factures", "year": 2020, "amount": 118.0, "date": "2020-03-05T00:00:00", "organization": "Ajuntament de Valls", "department": "21200-ACCIO CIVICA", "counterparty": "VIVES CORBELLA, PILAR", "title": "PILAR VIVES CORBELLA, IMPORT FRA.1/20, PRESENTACIÓ DEL ' BLAI VALLENC'", "reference": "1/20", "status": "Pagada", "is_cancelled": false, "source_file": "registre-factures__registre-de-factures-2020.csv", "raw_fields": {"_id": "779", "NOM_ENS": "Ajuntament de Valls", "CODI_ENS": "4316130008", "REFERENCIA": "20200000780", "EXERCICI": "2020", "REFERENCIA_FACTURA": "1/20", "ESTAT_FACTURA": "Pagada", "DATA_PRESENTACIO": "2020-03-05T12:54:32", "DATA_REGISTRE": "2020-03-05T12:54:32", "DATA_FACTURA": "2020-03-05T00:00:00", "DESCRIPCIO": "PILAR VIVES CORBELLA, IMPORT FRA.1/20, PRESENTACIÓ DEL ' BLAI VALLENC'", "TIPUS_ENTRADA": "Càrrec", "PROVEIDOR": "VIVES CORBELLA, PILAR", "DEPARTAMENT": "21200-ACCIO CIVICA", "IMPORT_TOTAL": "118.0000", "IMPORT_BRUT": "118.0000", "IVA": "0", "DESCOMPTE": "17.7000", "DATA_VENCIMENT": "2020-04-04T00:00:00", "DATA_INCORPORACIO": "2020-03-06T00:00:00", "DATA_COMPTABILITZACIO": "2020-03-12T00:00:00", "DATA_PAGAMENT": "2020-03-30T00:00:00", "LATITUD": "41.2842776", "LONGITUD": "1.2476852"}}, {"source": "invoices", "source_label": "Factures", "year": 2020, "amount": 91.0, "date": "2020-03-05T00:00:00", "organization": "Ajuntament de Valls", "department": "21200-ACCIO CIVICA", "counterparty": "VIVES CORBELLA, PILAR", "title": "PILAR VIVES CORBELLA, IMPORT FRA.2/20, PRESENTACIÓ DE LA CASSOLA DE DIJOUS GRAS AL CENTRE CÍVIC", "reference": "2/20", "status": "Pagada", "is_cancelled": false, "source_file": "registre-factures__registre-de-factures-2020.csv", "raw_fields": {"_id": "780", "NOM_ENS": "Ajuntament de Valls", "CODI_ENS": "4316130008", "REFERENCIA": "20200000781", "EXERCICI": "2020", "REFERENCIA_FACTURA": "2/20", "ESTAT_FACTURA": "Pagada", "DATA_PRESENTACIO": "2020-03-05T12:59:58", "DATA_REGISTRE": "2020-03-05T12:59:58", "DATA_FACTURA": "2020-03-05T00:00:00", "DESCRIPCIO": "PILAR VIVES CORBELLA, IMPORT FRA.2/20, PRESENTACIÓ DE LA CASSOLA DE DIJOUS GRAS AL CENTRE CÍVIC", "TIPUS_ENTRADA": "Càrrec", "PROVEIDOR": "VIVES CORBELLA, PILAR", "DEPARTAMENT": "21200-ACCIO CIVICA", "IMPORT_TOTAL": "91.0000", "IMPORT_BRUT": "91.0000", "IVA": "0", "DESCOMPTE": "13.6500", "DATA_VENCIMENT": "2020-04-04T00:00:00", "DATA_INCORPORACIO": "2020-03-06T00:00:00", "DATA_COMPTABILITZACIO": "2020-03-12T00:00:00", "DATA_PAGAMENT": "2020-03-30T00:00:00", "LATITUD": "41.2842776", "LONGITUD": "1.2476852"}}, {"source": "contracts", "source_label": "Contractes menors", "year": 2020, "amount": 118.0, "date": "2020-02-27T00:00:00", "organization": "Ajuntament de Valls", "department": "ACCIÓ CÍVICA", "counterparty": "VIVES CORBELLA, PILAR", "title": "Presentació del \" Blai vallenc\"", "reference": "CM-2020-0000332", "status": "Serveis", "is_cancelled": false, "source_file": "contractacio__contractes-menors-2020.csv", "raw_fields": {"_id": "278", "NOM_ENS": "Ajuntament de Valls", "CODI_ENS": "4316130008", "EXPEDIENT": "CM-2020-0000332", "DATA_ADJUDICACIO": "2020-02-27T00:00:00", "DESCRIPCIO": "Presentació del \" Blai vallenc\"", "DEPARTAMENT": "ACCIÓ CÍVICA", "TIPUS": "Serveis", "NOM_ADJ": "VIVES CORBELLA, PILAR", "CIF_ADJ": "****9989*", "POBLACIO_ADJ": "Valls", "PROVINCIA_ADJ": "Tarragona", "IMPORT": "118.0", "LATITUD": "41.2842776", "LONGITUD": "1.2476852"}}, {"source": "contracts", "source_label": "Contractes menors", "year": 2020, "amount": 91.0, "date": "2020-02-27T00:00:00", "organization": "Ajuntament de Valls", "department": "ACCIÓ CÍVICA", "counterparty": "VIVES CORBELLA, PILAR", "title": "Presentació de la cassola de dijous gras al Centre Cívic", "reference": "CM-2020-0000333", "status": "Serveis", "is_cancelled": false, "source_file": "contractacio__contractes-menors-2020.csv", "raw_fields": {"_id": "277", "NOM_ENS": "Ajuntament de Valls", "CODI_ENS": "4316130008", "EXPEDIENT": "CM-2020-0000333", "DATA_ADJUDICACIO": "2020-02-27T00:00:00", "DESCRIPCIO": "Presentació de la cassola de dijous gras al Centre Cívic", "DEPARTAMENT": "ACCIÓ CÍVICA", "TIPUS": "Serveis", "NOM_ADJ": "VIVES CORBELLA, PILAR", "CIF_ADJ": "****9989*", "POBLACIO_ADJ": "Valls", "PROVINCIA_ADJ": "Tarragona", "IMPORT": "91.0", "LATITUD": "41.2842776", "LONGITUD": "1.2476852"}}]}