{"id": "entity:sgs-tecnos-s-a", "file": "entity-sgs-tecnos-s-a.json", "kind": "entity", "name": "SGS TECNOS, S.A.", "cif": "A28345577", "city": "Madrid", "province": "Madrid", "organization": "Ajuntament de Valls", "record_count": 14, "visible_record_count": 14, "total_amount": 181862.04, "display_amount": 82167.44999999997, "display_count": 10, "display_source": "invoices", "years": {"2021": {"amount": 35054.16, "count": 6}, "2020": {"amount": 17527.14, "count": 1}, "2017": {"amount": 23569.88, "count": 2}, "2016": {"amount": 105710.85999999999, "count": 5}}, "sources": {"contracts": {"amount": 17527.14, "count": 1}, "supplier_spend": {"amount": 82167.45000000001, "count": 3}, "invoices": {"amount": 82167.44999999997, "count": 10}}, "records": [{"source": "supplier_spend", "source_label": "Despesa per proveïdor", "year": 2021, "amount": 17527.08, "date": "2021-12-31", "organization": "Ajuntament de Valls", "department": "", "counterparty": "SGS TECNOS, S.A.", "title": "Import total facturat pel proveïdor a 2021", "reference": "A28345577", "status": "", "is_cancelled": false, "source_file": "proveidors__despesa-per-prove-dor-2021.csv", "raw_fields": {"_id": "54", "NOM_ENS": "Ajuntament de Valls", "CODI_ENS": "4316130008", "PROVEIDOR": "SGS TECNOS, S.A.", "CIF": "A28345577", "POBL_ENT": "Madrid", "PROV_ENT": "Madrid", "IMPORT_FACTURAT": "17527.0800", "LATITUD": "41.2842776", "LONGITUD": "1.2476852"}}, {"source": "invoices", "source_label": "Factures", "year": 2021, "amount": 2921.18, "date": "2021-09-08T00:00:00", "organization": "Ajuntament de Valls", "department": "GRANS PROJECTES INTEGRALS", "counterparty": "SGS TECNOS, S.A.", "title": "SGS TECNOS, S.A., IMPORT FRA.02901143673, DIRECCIÓ EXECUTIVA D'OBRA I COORDINACIÓ DE SEGURETAT I SALUT (ARQUITECTE TÈCNIC-APARELLADOR) (just 100% OSIC 2023)", "reference": "02901143673", "status": "Pagada", "is_cancelled": false, "source_file": "registre-factures__registre-de-factures-2021.csv", "raw_fields": {"_id": "3232", "NOM_ENS": "Ajuntament de Valls", "CODI_ENS": "4316130008", "REFERENCIA": "20210003229", "EXERCICI": "2021", "REFERENCIA_FACTURA": "02901143673", "ESTAT_FACTURA": "Pagada", "DATA_PRESENTACIO": "2021-09-09T11:28:58", "DATA_REGISTRE": "2021-09-09T11:28:58", "DATA_FACTURA": "2021-09-08T00:00:00", "DESCRIPCIO": "SGS TECNOS, S.A., IMPORT FRA.02901143673, DIRECCIÓ EXECUTIVA D'OBRA I COORDINACIÓ DE SEGURETAT I SALUT (ARQUITECTE TÈCNIC-APARELLADOR) (just 100% OSIC 2023)", "TIPUS_ENTRADA": "Càrrec", "PROVEIDOR": "SGS TECNOS, S.A.", "DEPARTAMENT": "40310-GRANS PROJECTES INTEGRALS", "IMPORT_TOTAL": "2921.1800", "IMPORT_BRUT": "2414.2000", "IVA": "506.9800", "DESCOMPTE": "0", "DATA_VENCIMENT": "2021-10-09T00:00:00", "DATA_INCORPORACIO": "2021-09-10T00:00:00", "DATA_COMPTABILITZACIO": "2021-09-16T00:00:00", "DATA_PAGAMENT": "2021-09-28T00:00:00", "LATITUD": "41.2842776", "LONGITUD": "1.2476852"}}, {"source": "invoices", "source_label": "Factures", "year": 2021, "amount": 2921.18, "date": "2021-07-14T00:00:00", "organization": "Ajuntament de Valls", "department": "GRANS PROJECTES INTEGRALS", "counterparty": "SGS TECNOS, S.A.", "title": "SGS TECNOS, S.A., IMPORT FRA.2901142567, DIRECCIÓ EXECUTIVA D'OBRA I COORDINACIÓ DE SEGURETAT I SALUT (ARQUITECTE TÈCNIC-APARELLADOR) (just 100% OSIC 2023)", "reference": "02901142567", "status": "Pagada", "is_cancelled": false, "source_file": "registre-factures__registre-de-factures-2021.csv", "raw_fields": {"_id": "2524", "NOM_ENS": "Ajuntament de Valls", "CODI_ENS": "4316130008", "REFERENCIA": "20210002512", "EXERCICI": "2021", "REFERENCIA_FACTURA": "02901142567", "ESTAT_FACTURA": "Pagada", "DATA_PRESENTACIO": "2021-07-15T10:40:02", "DATA_REGISTRE": "2021-07-15T10:40:02", "DATA_FACTURA": "2021-07-14T00:00:00", "DESCRIPCIO": "SGS TECNOS, S.A., IMPORT FRA.2901142567, DIRECCIÓ EXECUTIVA D'OBRA I COORDINACIÓ DE SEGURETAT I SALUT (ARQUITECTE TÈCNIC-APARELLADOR) (just 100% OSIC 2023)", "TIPUS_ENTRADA": "Càrrec", "PROVEIDOR": "SGS TECNOS, S.A.", "DEPARTAMENT": "40310-GRANS PROJECTES INTEGRALS", "IMPORT_TOTAL": "2921.1800", "IMPORT_BRUT": "2414.2000", "IVA": "506.9800", "DESCOMPTE": "0", "DATA_VENCIMENT": "2021-08-14T00:00:00", "DATA_INCORPORACIO": "2021-08-27T00:00:00", "DATA_COMPTABILITZACIO": "2021-09-02T00:00:00", "DATA_PAGAMENT": "2021-09-06T00:00:00", "LATITUD": "41.2842776", "LONGITUD": "1.2476852"}}, {"source": "invoices", "source_label": "Factures", "year": 2021, "amount": 2921.18, "date": "2021-06-03T00:00:00", "organization": "Ajuntament de Valls", "department": "GRANS PROJECTES INTEGRALS", "counterparty": "SGS TECNOS, S.A.", "title": "SGS TECNOS, S.A., IMPORT FRA.2901141783, DIRECCIÓ EXECUTIVA D'OBRA I COORDINACIÓ DE SEGURETAT I SALUT (ARQUITECTE TÈCNIC-APARELLADOR) (just 100% OSIC 2023)", "reference": "02901141783", "status": "Pagada", "is_cancelled": false, "source_file": "registre-factures__registre-de-factures-2021.csv", "raw_fields": {"_id": "1982", "NOM_ENS": "Ajuntament de Valls", "CODI_ENS": "4316130008", "REFERENCIA": "20210001974", "EXERCICI": "2021", "REFERENCIA_FACTURA": "02901141783", "ESTAT_FACTURA": "Pagada", "DATA_PRESENTACIO": "2021-06-04T08:20:07", "DATA_REGISTRE": "2021-06-04T08:20:07", "DATA_FACTURA": "2021-06-03T00:00:00", "DESCRIPCIO": "SGS TECNOS, S.A., IMPORT FRA.2901141783, DIRECCIÓ EXECUTIVA D'OBRA I COORDINACIÓ DE SEGURETAT I SALUT (ARQUITECTE TÈCNIC-APARELLADOR) (just 100% OSIC 2023)", "TIPUS_ENTRADA": "Càrrec", "PROVEIDOR": "SGS TECNOS, S.A.", "DEPARTAMENT": "40310-GRANS PROJECTES INTEGRALS", "IMPORT_TOTAL": "2921.1800", "IMPORT_BRUT": "2414.2000", "IVA": "506.9800", "DESCOMPTE": "0", "DATA_VENCIMENT": "2021-07-04T00:00:00", "DATA_INCORPORACIO": "2021-06-11T00:00:00", "DATA_COMPTABILITZACIO": "2021-06-17T00:00:00", "DATA_PAGAMENT": "2021-06-23T00:00:00", "LATITUD": "41.2842776", "LONGITUD": "1.2476852"}}, {"source": "invoices", "source_label": "Factures", "year": 2021, "amount": 2921.18, "date": "2021-05-04T00:00:00", "organization": "Ajuntament de Valls", "department": "GRANS PROJECTES INTEGRALS", "counterparty": "SGS TECNOS, S.A.", "title": "SGS TECNOS, S.A., IMPORT FRA.2901141080, DIRECCIÓ EXECUTIVA D'OBRA I COORDINACIÓ DE SEGURETAT I SALUT (ARQUITECTE TÈCNIC-APARELLADOR) (just 100% OSIC 2023)", "reference": "02901141080", "status": "Pagada", "is_cancelled": false, "source_file": "registre-factures__registre-de-factures-2021.csv", "raw_fields": {"_id": "1572", "NOM_ENS": "Ajuntament de Valls", "CODI_ENS": "4316130008", "REFERENCIA": "20210001569", "EXERCICI": "2021", "REFERENCIA_FACTURA": "02901141080", "ESTAT_FACTURA": "Pagada", "DATA_PRESENTACIO": "2021-05-05T08:12:21", "DATA_REGISTRE": "2021-05-05T08:12:21", "DATA_FACTURA": "2021-05-04T00:00:00", "DESCRIPCIO": "SGS TECNOS, S.A., IMPORT FRA.2901141080, DIRECCIÓ EXECUTIVA D'OBRA I COORDINACIÓ DE SEGURETAT I SALUT (ARQUITECTE TÈCNIC-APARELLADOR) (just 100% OSIC 2023)", "TIPUS_ENTRADA": "Càrrec", "PROVEIDOR": "SGS TECNOS, S.A.", "DEPARTAMENT": "40310-GRANS PROJECTES INTEGRALS", "IMPORT_TOTAL": "2921.1800", "IMPORT_BRUT": "2414.2000", "IVA": "506.9800", "DESCOMPTE": "0", "DATA_VENCIMENT": "2021-06-04T00:00:00", "DATA_INCORPORACIO": "2021-05-19T00:00:00", "DATA_COMPTABILITZACIO": "2021-05-27T00:00:00", "DATA_PAGAMENT": "2021-06-09T00:00:00", "LATITUD": "41.2842776", "LONGITUD": "1.2476852"}}, {"source": "invoices", "source_label": "Factures", "year": 2021, "amount": 5842.36, "date": "2021-04-09T00:00:00", "organization": "Ajuntament de Valls", "department": "GRANS PROJECTES INTEGRALS", "counterparty": "SGS TECNOS, S.A.", "title": "SGS TECNOS, S.A., IMPORT FRA.2901140426, DIRECCIÓ EXECUTIVA D'OBRA I COORDINACIÓ DE SEGURETAT I SALUT (ARQUITECTE TÈCNIC-APARELLADOR) (just 100% OSIC 2023)", "reference": "02901140426", "status": "Pagada", "is_cancelled": false, "source_file": "registre-factures__registre-de-factures-2021.csv", "raw_fields": {"_id": "1265", "NOM_ENS": "Ajuntament de Valls", "CODI_ENS": "4316130008", "REFERENCIA": "20210001263", "EXERCICI": "2021", "REFERENCIA_FACTURA": "02901140426", "ESTAT_FACTURA": "Pagada", "DATA_PRESENTACIO": "2021-04-09T15:26:54", "DATA_REGISTRE": "2021-04-09T15:26:54", "DATA_FACTURA": "2021-04-09T00:00:00", "DESCRIPCIO": "SGS TECNOS, S.A., IMPORT FRA.2901140426, DIRECCIÓ EXECUTIVA D'OBRA I COORDINACIÓ DE SEGURETAT I SALUT (ARQUITECTE TÈCNIC-APARELLADOR) (just 100% OSIC 2023)", "TIPUS_ENTRADA": "Càrrec", "PROVEIDOR": "SGS TECNOS, S.A.", "DEPARTAMENT": "40310-GRANS PROJECTES INTEGRALS", "IMPORT_TOTAL": "5842.3600", "IMPORT_BRUT": "4828.4000", "IVA": "1013.9600", "DESCOMPTE": "0", "DATA_VENCIMENT": "2021-05-09T00:00:00", "DATA_INCORPORACIO": "2021-05-19T00:00:00", "DATA_COMPTABILITZACIO": "2021-05-27T00:00:00", "DATA_PAGAMENT": "2021-06-09T00:00:00", "LATITUD": "41.2842776", "LONGITUD": "1.2476852"}}, {"source": "contracts", "source_label": "Contractes menors", "year": 2020, "amount": 17527.14, "date": "2020-09-24T00:00:00", "organization": "Ajuntament de Valls", "department": "ACT. PUBLIQUS (Antic GRANS PROJECTES INTEGRALS)", "counterparty": "SGS TECNOS, S.A.", "title": "DIRECCIÓ EXECUTIVA D'OBRA i COORDINACIÓ DE SEGURETAT I SALUT (ARQUITECTE TÈCNIC-APARELLADOR)", "reference": "CM-2020-0001020", "status": "Serveis", "is_cancelled": false, "source_file": "contractacio__contractes-menors-2020.csv", "raw_fields": {"_id": "838", "NOM_ENS": "Ajuntament de Valls", "CODI_ENS": "4316130008", "EXPEDIENT": "CM-2020-0001020", "DATA_ADJUDICACIO": "2020-09-24T00:00:00", "DESCRIPCIO": "DIRECCIÓ EXECUTIVA D'OBRA i COORDINACIÓ DE SEGURETAT I SALUT (ARQUITECTE TÈCNIC-APARELLADOR)", "DEPARTAMENT": "ACT. PUBLIQUS (Antic GRANS PROJECTES INTEGRALS)", "TIPUS": "Serveis", "NOM_ADJ": "SGS TECNOS, S.A.", "CIF_ADJ": "A28345577", "POBLACIO_ADJ": "Madrid", "PROVINCIA_ADJ": "Madrid", "IMPORT": "17527.14", "LATITUD": "41.2842776", "LONGITUD": "1.2476852"}}, {"source": "supplier_spend", "source_label": "Despesa per proveïdor", "year": 2017, "amount": 11784.94, "date": "2017-12-31", "organization": "Ajuntament de Valls", "department": "", "counterparty": "SGS TECNOS, S.A.", "title": "Import total facturat pel proveïdor a 2017", "reference": "A28345577", "status": "", "is_cancelled": false, "source_file": "proveidors__despesa-per-prove-dor-2017.csv", "raw_fields": {"_id": "183", "NOM_ENS": "Ajuntament de Valls", "CODI_ENS": "4316130008", "PROVEIDOR": "SGS TECNOS, S.A.", "CIF": "A28345577", "POBL_ENT": "Madrid", "PROV_ENT": "Madrid", "IMPORT_FACTURAT": "11784.9400", "LATITUD": "41.2842776", "LONGITUD": "1.2476852"}}, {"source": "invoices", "source_label": "Factures", "year": 2017, "amount": 11784.94, "date": "2017-02-28T00:00:00", "organization": "Ajuntament de Valls", "department": "URBANISME", "counterparty": "SGS TECNOS, S.A.", "title": "SGS TECNOS, SA, IMPORT FRA. 02-901-105602, DIRECCIÓ EXECUCIÓ I COORDINACIÓ DE SEGURETAT OBRA MUSEU CASTELLER", "reference": "02-901-105602", "status": "Pagada", "is_cancelled": false, "source_file": "registre-factures__registre-de-factures-2017.csv", "raw_fields": {"_id": "3956", "NOM_ENS": "Ajuntament de Valls", "CODI_ENS": "4316130008", "REFERENCIA": "20170000558", "EXERCICI": "2017", "REFERENCIA_FACTURA": "02-901-105602", "ESTAT_FACTURA": "Pagada", "DATA_PRESENTACIO": "2017-02-28T09:40:00", "DATA_REGISTRE": "2017-03-01T08:33:18", "DATA_FACTURA": "2017-02-28T00:00:00", "DESCRIPCIO": "SGS TECNOS, SA, IMPORT FRA. 02-901-105602, DIRECCIÓ EXECUCIÓ I COORDINACIÓ DE SEGURETAT OBRA MUSEU CASTELLER", "TIPUS_ENTRADA": "Càrrec", "PROVEIDOR": "SGS TECNOS, S.A.", "DEPARTAMENT": "51101-URBANISME", "IMPORT_TOTAL": "11784.9400", "IMPORT_BRUT": "9739.6200", "IVA": "2045.3200", "DESCOMPTE": "0", "DATA_VENCIMENT": "2017-04-29T00:00:00", "DATA_INCORPORACIO": "2017-03-16T00:00:00", "DATA_COMPTABILITZACIO": "2017-03-17T00:00:00", "DATA_PAGAMENT": "2017-04-28T00:00:00", "LATITUD": "41.2842776", "LONGITUD": "1.2476852"}}, {"source": "supplier_spend", "source_label": "Despesa per proveïdor", "year": 2016, "amount": 52855.43, "date": "2016-12-31", "organization": "Ajuntament de Valls", "department": "", "counterparty": "SGS TECNOS, S.A.", "title": "Import total facturat pel proveïdor a 2016", "reference": "A28345577", "status": "", "is_cancelled": false, "source_file": "proveidors__despesa-per-prove-dor-2016.csv", "raw_fields": {"_id": "20", "NOM_ENS": "Ajuntament de Valls", "CODI_ENS": "4316130008", "PROVEIDOR": "SGS TECNOS, S.A.", "CIF": "A28345577", "POBL_ENT": "Madrid", "PROV_ENT": "Madrid", "IMPORT_FACTURAT": "52855.4300", "LATITUD": "41.2842776", "LONGITUD": "1.2476852"}}, {"source": "invoices", "source_label": "Factures", "year": 2016, "amount": 15182.49, "date": "2016-11-22T00:00:00", "organization": "Ajuntament de Valls", "department": "URBANISME", "counterparty": "SGS TECNOS, S.A.", "title": "SGS TECNOS, SA, IMPORT FRA.02-901-103309, DIRECCIÓ EXECUCIÓ I COORDINACIÓ DE SEGURETAT OBRA MUSEU CASTELLER", "reference": "02-901-103309", "status": "Pagada", "is_cancelled": false, "source_file": "registre-factures__registre-de-factures-2016.csv", "raw_fields": {"_id": "653", "NOM_ENS": "Ajuntament de Valls", "CODI_ENS": "4316130008", "REFERENCIA": "20160003480", "EXERCICI": "2016", "REFERENCIA_FACTURA": "02-901-103309", "ESTAT_FACTURA": "Pagada", "DATA_PRESENTACIO": "2016-11-23T13:44:00", "DATA_REGISTRE": "2016-11-23T15:58:38", "DATA_FACTURA": "2016-11-22T00:00:00", "DESCRIPCIO": "SGS TECNOS, SA, IMPORT FRA.02-901-103309, DIRECCIÓ EXECUCIÓ I COORDINACIÓ DE SEGURETAT OBRA MUSEU CASTELLER", "TIPUS_ENTRADA": "Càrrec", "PROVEIDOR": "SGS TECNOS, S.A.", "DEPARTAMENT": "51101-URBANISME", "IMPORT_TOTAL": "15182.4900", "IMPORT_BRUT": "12547.5100", "IVA": "2634.9800", "DESCOMPTE": "0", "DATA_VENCIMENT": "2017-01-21T00:00:00", "DATA_INCORPORACIO": "2016-12-07T00:00:00", "DATA_COMPTABILITZACIO": "2016-12-09T00:00:00", "DATA_PAGAMENT": "2017-01-23T00:00:00", "LATITUD": "41.2842776", "LONGITUD": "1.2476852"}}, {"source": "invoices", "source_label": "Factures", "year": 2016, "amount": 18219.1, "date": "2016-08-30T00:00:00", "organization": "Ajuntament de Valls", "department": "URBANISME", "counterparty": "SGS TECNOS, S.A.", "title": "SGS TECNOS, SA, IMPORT FRA.02-901-101913, DIRECCIÓ EXECUCIÓ I COORDINACIÓ DE SEGURETAT OBRA MUSEU CASTELLER", "reference": "02-901-101913", "status": "Pagada", "is_cancelled": false, "source_file": "registre-factures__registre-de-factures-2016.csv", "raw_fields": {"_id": "1500", "NOM_ENS": "Ajuntament de Valls", "CODI_ENS": "4316130008", "REFERENCIA": "20160002515", "EXERCICI": "2016", "REFERENCIA_FACTURA": "02-901-101913", "ESTAT_FACTURA": "Pagada", "DATA_PRESENTACIO": "2016-09-01T12:47:00", "DATA_REGISTRE": "2016-09-02T08:23:45", "DATA_FACTURA": "2016-08-30T00:00:00", "DESCRIPCIO": "SGS TECNOS, SA, IMPORT FRA.02-901-101913, DIRECCIÓ EXECUCIÓ I COORDINACIÓ DE SEGURETAT OBRA MUSEU CASTELLER", "TIPUS_ENTRADA": "Càrrec", "PROVEIDOR": "SGS TECNOS, S.A.", "DEPARTAMENT": "51101-URBANISME", "IMPORT_TOTAL": "18219.1000", "IMPORT_BRUT": "15057.1100", "IVA": "3161.9900", "DESCOMPTE": "0", "DATA_VENCIMENT": "2016-10-29T00:00:00", "DATA_INCORPORACIO": "2016-09-07T00:00:00", "DATA_COMPTABILITZACIO": "2016-09-09T00:00:00", "DATA_PAGAMENT": "2016-10-28T00:00:00", "LATITUD": "41.2842776", "LONGITUD": "1.2476852"}}, {"source": "invoices", "source_label": "Factures", "year": 2016, "amount": 9310.42, "date": "2016-04-27T00:00:00", "organization": "Ajuntament de Valls", "department": "URBANISME", "counterparty": "SGS TECNOS, S.A.", "title": "SGS TECNOS, SA, IMPORT FRA. 02-901-89580, DIRECCIÓ EXECUCIÓ I COORDINACIÓ DE SEGURETAT OBRA MUSEU CASTELLER (4 FACTURA)", "reference": "02-901-89580", "status": "Pagada", "is_cancelled": false, "source_file": "registre-factures__registre-de-factures-2016.csv", "raw_fields": {"_id": "2643", "NOM_ENS": "Ajuntament de Valls", "CODI_ENS": "4316130008", "REFERENCIA": "20160001244", "EXERCICI": "2016", "REFERENCIA_FACTURA": "02-901-89580", "ESTAT_FACTURA": "Pagada", "DATA_PRESENTACIO": "2016-04-28T11:57:00", "DATA_REGISTRE": "2016-04-28T13:37:33", "DATA_FACTURA": "2016-04-27T00:00:00", "DESCRIPCIO": "SGS TECNOS, SA, IMPORT FRA. 02-901-89580, DIRECCIÓ EXECUCIÓ I COORDINACIÓ DE SEGURETAT OBRA MUSEU CASTELLER (4 FACTURA)", "TIPUS_ENTRADA": "Càrrec", "PROVEIDOR": "SGS TECNOS, S.A.", "DEPARTAMENT": "51101-URBANISME", "IMPORT_TOTAL": "9310.4200", "IMPORT_BRUT": "7694.5600", "IVA": "1615.8600", "DESCOMPTE": "0", "DATA_VENCIMENT": "2016-06-26T00:00:00", "DATA_INCORPORACIO": "2016-05-19T00:00:00", "DATA_COMPTABILITZACIO": "2016-05-20T00:00:00", "DATA_PAGAMENT": "2016-06-23T00:00:00", "LATITUD": "41.2842776", "LONGITUD": "1.2476852"}}, {"source": "invoices", "source_label": "Factures", "year": 2016, "amount": 10143.42, "date": "2016-01-27T00:00:00", "organization": "Ajuntament de Valls", "department": "URBANISME", "counterparty": "SGS TECNOS, S.A.", "title": "SGS TECNOS, SA, IMPORT FRA. 02-901-87997, CONTRACTE DE SERVEIS DIRECCIÓ FACULTATIVA, DIRECCIÓ D'EXECUCIÓ I COORDINACIÓ DE SEGURETAT I SALUT DE L'OBRA DE CONSTRUCCIÓ DEL MUSEU CASTELLER. 3ª FACTURA", "reference": "02-901-87997", "status": "Pagada", "is_cancelled": false, "source_file": "registre-factures__registre-de-factures-2016.csv", "raw_fields": {"_id": "3789", "NOM_ENS": "Ajuntament de Valls", "CODI_ENS": "4316130008", "REFERENCIA": "20160000206", "EXERCICI": "2016", "REFERENCIA_FACTURA": "02-901-87997", "ESTAT_FACTURA": "Pagada", "DATA_PRESENTACIO": "2016-01-27T15:56:54", "DATA_REGISTRE": "2016-01-27T15:56:54", "DATA_FACTURA": "2016-01-27T00:00:00", "DESCRIPCIO": "SGS TECNOS, SA, IMPORT FRA. 02-901-87997, CONTRACTE DE SERVEIS DIRECCIÓ FACULTATIVA, DIRECCIÓ D'EXECUCIÓ I COORDINACIÓ DE SEGURETAT I SALUT DE L'OBRA DE CONSTRUCCIÓ DEL MUSEU CASTELLER. 3ª FACTURA", "TIPUS_ENTRADA": "Càrrec", "PROVEIDOR": "SGS TECNOS, S.A.", "DEPARTAMENT": "51101-URBANISME", "IMPORT_TOTAL": "10143.4200", "IMPORT_BRUT": "8382.9900", "IVA": "1760.4300", "DESCOMPTE": "0", "DATA_VENCIMENT": "2016-03-27T00:00:00", "DATA_INCORPORACIO": "2016-03-10T00:00:00", "DATA_COMPTABILITZACIO": "2016-03-11T00:00:00", "DATA_PAGAMENT": "2016-03-21T00:00:00", "LATITUD": "41.2842776", "LONGITUD": "1.2476852"}}]}